Workbook

Sheet Read me
A1: Time ships after Chrysalis — design sheet
A2: Built 8 October 2026 from the brainstorm 'time travel spacecraft similar to Chrysalis'. Every number is a live formula over the blue inputs; change a distance, an acceleration, a radius or a mass and the leads, stresses and bills follow.
A4: THE IDEA | B4: Chrysalis is already a time machine, just a slow one of the kind a cesium clock can measure: at 1 g its rim clocks run ~14 ns/day behind the hub, and over its 400-year crossing at ~1% of c the passengers step off about eight days younger than Earth's calendar. So the brief for a time ship is: make the lead bigger, and decide whose clock you're cheating. Keep the five coats, swap the core.
A6: Legend | B6: Blue text = an input you can change. Black = a formula. Green = a link to another sheet. Yellow fill = an assumption worth questioning. The Notes column carries the reasoning and the source for each line.
A8: SHEETS
A9: Four cores | B9: The four designs side by side: what replaces the shuttle bay, the physics status, the lead and the bill (live).
A10: Chrysalis | B10: The baseline as reported: geometry, cruise speed, spin gravity and the clocks aboard, hoop stress (and the Tipler check), the 400-year lead, fuel, people, and what the nose ploughs through.
A11: Lead table | B11: Seven ships (two are yours to play with): ship time, Earth time, lead, peak speed, mass ratio, and the light-time the Lantern needs. Includes a 1 g lead-vs-distance chart.
A12: Tower | B12: The dilation ship: thrust gravity, the engine's power, floors and lifts, the prow-to-stern clock gradient, the ice shield, and the crew's arrival.
A13: Lantern | B13: The wormhole door: the negative-mass bill, how deep the door goes for each ship, and whether a closed timelike curve forms.
A14: Nautilus | B14: The archive ship: how much it can grow from its own spent tankage, the walk back through time, spin balance, and each era's clock.
A15: Vigil | B15: The cold-storage ship: the roster arithmetic, the pods, the speed bonus from a lighter ship, and the 40-watch calendar.
A16: More cores | B16: The second wing (9 Oct 2026): ferry, shed hull, broadcast, homebody — side by side, live.
A17: Pendulum | B17: The ferry: 1 g out and home; the timetable of futures a ticket buys, and the fare that closes the ferry.
A18: Moult | B18: The shed hull: jettison emptied shells before the brake; a quadratic turns casings into cruise speed (0% moult reproduces Chrysalis exactly).
A19: Lighthouse | B19: The broadcast: the voyage as a 404-year slow-motion transmission; Doppler, latency, and photons per second across four light-years.
A20: Sundiver | B20: The homebody: Sun-grazing orbits bank seconds per pass, and the honest verdict — the wheel beats the well 3,900 to 1.
A21: Constants | B21: Physical constants with sources, the shared assumptions (interstellar density, dust ratio), the project's own clocks for scale, and the materials table.
A23: CAVEATS
A24: Chrysalis figures | B24: From press coverage of the Project Hyperion entry (58 km, 6 km, 2.4 billion t, 2,400 people, 400 years, 40 trillion km). The team's own report may differ; the inputs are blue so you can correct them.
A25: Orders of magnitude | B25: The torch rows assume a perfect photon rocket (the floor on the fuel bill). The ice-shield mass is an upper bound (every joule sublimates ice). The wormhole mass is the Morris–Thorne order of magnitude. Hoop stress is for a self-supporting thin shell. None of this is a design; all of it is a sanity check.
A26: Corrections to the spoken version | B26: Three things the formulas overturned. (1) The peak proton flux on the prow is ~300 kW/m², not 100: the ship-frame density is γn. (2) 'The prow is a glacier' fails: a sacrificial ice prow the full width of the ship needs ~66 Gt at n = 1 cm⁻³ (27 ships' worth, a 2.5-km slab), not 30 Mt — so the Tower needs a needle prow, a refractory bow that re-radiates at ~1,500 K, or a magnetic deflector; the Tower sheet now checks the refractory option. (3) The Proxima torch's ship time is 3.5 years at 4.2465 ly (3.6 is the usual round figure). Everything else checks out.
A28: SOURCES
B29: Project Hyperion Design Competition results — https://projecthyperion.org/
B30: Centauri Dreams, 'Chrysalis: Designing a Generation Ship' (12 Aug 2025) — https://www.centauri-dreams.org/2025/08/12/chrysalis-designing-a-generation-ship/
B31: Holistic News, 'This Starship Could Take Us to the Stars' — https://holistic.news/en/journey-to-alpha-centauri-a-ship-is-designed/
B32: ITC.ua, 'Chrysalis: an interstellar ship project to travel 2400 people for 400 years' — https://itc.ua/en/news/chrysalis-an-interstellar-ship-project-to-travel-2400-people-for-400-years
B33: Futura-Sciences, Chrysalis coverage — https://www.futura-sciences.com/en/?p=20696
B34: Interesting Engineering, '36-mile-long cigar-shaped starship' — https://interestingengineering.com/space/engineers-propose-multi-generational-spacecraft
B35: Indian Defence Review, 'No return, no rescue: meet Chrysalis' — https://indiandefencereview.com/no-return-no-rescue-meet-chrysalis-the-36-mile-starship-designed-to-carry-1000-humans-into-deep-space-forever/
B36: Morris, Thorne & Yurtsever, 'Wormholes, Time Machines, and the Weak Energy Condition', Phys. Rev. Lett. 61, 1446 (1988)
B37: Hawking, 'Chronology protection conjecture', Phys. Rev. D 46, 603 (1992)
B38: Tipler, 'Rotating cylinders and the possibility of global causality violation', Phys. Rev. D 9, 2203 (1974)
B39: Vessot et al., Gravity Probe A, Phys. Rev. Lett. 45, 2081 (1980) — 7×10⁻⁵ test of gravitational redshift
B40: The Greylock Time Machine design note — Time Travel project, claude/greylock-time-machine.md
B41: Constants: CODATA 2018; IAU 2015 nominal values; Lee et al., Science 321, 385 (2008) for graphene

Sheet Four cores
A1: Four cores — keep Chrysalis's five coats, swap the core
A2: Chrysalis is five concentric shells around a core that holds the landing shuttles and the main comms. Each design below keeps the shells and replaces the core. Numbers are live links to the other sheets.
B4: TOWER — the engine | C4: LANTERN — the door | D4: NAUTILUS — the archive | E4: VIGIL — the vault
A5: What replaces the shuttle bay | B5: The engine. Thrust is gravity: 'down' is aft and the five shells become stacked floors of a 58-km tower standing on its exhaust. | C5: A wormhole mouth. Its twin stays at the Earth–Moon L1 yard where the ship was built; the core stops being an axis and becomes a point, so the shells nest as spheres round a lantern room. | D5: An archive. Each generation builds the next chamber onto the axis and seals the one it grew up in exactly as it was lived — lights on, cups on the table. | E5: A vault. Cold storage for everyone not on watch; sixty awake at a time in ten-year watches.
A6: Gravity | B6: Thrust, 1 g aft (spin gravity gives way) | C6: Spin | D6: Spin — balanced as the ship grows | E6: Spin
A7: Physics status | B7: Known physics: forward time dilation, measured to 7×10⁻⁵ (Gravity Probe A). The bill is engineering. | C7: Permitted on paper (Morris–Thorne–Yurtsever 1988) but needs negative energy in bulk, which quantum theory forbids. Chronology protection waits past the speed limit. | D7: Known physics: civil engineering and archiving. | E7: Needs reversible human cold storage — the one technology here that does not exist.
A8: Direction of travel | B8: Forward only | C8: Backward — to a moment after the ship left, never before | D8: Forward; the archive lets the future stand in the past, in place | E8: Forward, by skipping
A9: Lead (live) | B9: =Tower!$B$31 -> 2.3 years | C9: =Lantern!$B$22&" — "&Lantern!$B$26 -> 2.3 years — No closed timelike curve: the door is safe | D9: ='Lead table'!$R$5&" (Chrysalis as drawn)" -> 8.2 days (Chrysalis as drawn) | E9: =TEXT(Vigil!$B$29,"0")&" years skipped per person, plus "&'Lead table'!$R$5&" of relativistic lead" -> 390 years skipped per person, plus 8.2 days of relativistic lead
A10: Who ages less | B10: The crew | C10: The ship's mouth, so the door opens onto the past | D10: Nobody to speak of; the time travel is cultural | E10: Everyone asleep
A11: The bill (live) | B11: =TEXT(Tower!$B$32-1,"#,##0")&" t of fuel per t of ship; one Sun per "&TEXT(Tower!$B$50,"#,##0")&" ships at dry mass" -> 38 t of fuel per t of ship; one Sun per 54,252 ships at dry mass | C11: ="About "&TEXT(Lantern!$B$14,"0.0")&" Jupiter masses of negative mass for a "&TEXT(Lantern!$B$7,"0")&" m throat" -> About 1.4 Jupiter masses of negative mass for a 2 m throat | D11: ="Spent tankage builds "&TEXT(Nautilus!$B$31,"0%")&" of the wished-for chambers: "&TEXT(Nautilus!$B$32,"#,##0")&" m per generation is affordable" -> Spent tankage builds 18% of the wished-for chambers: 184 m per generation is affordable | E11: ="Cold storage for "&TEXT(Vigil!$B$33,"#,##0")&" people at a time; "&TEXT(Vigil!$B$35,"#,##0")&" kW to hold them" -> Cold storage for 2,340 people at a time; 351 kW to hold them
A12: The human problem | B12: Nobody is born en route; the crew are the travellers, and no mission control waits at the far end. The ship must carry its own Earth. | C12: It deletes the one thing that defines a generation ship — isolation — and replaces it with something stranger: you can go home whenever you like, but home is always a little in the past. | D12: Deciding what a generation is allowed to leave out. The Hyperion jury said only Chrysalis took intergenerational meaning-making seriously; this is that, built into the hull. | E12: Rip Van Winkle in reverse: each watch is a different century's people, and the sleepers wake as strangers to those who kept them.
A13: Stacks with | B13: Nautilus as its interior; Vigil for the galactic-centre dial | C13: Nautilus | D13: Tower, Lantern | E13: Tower
A14: Sheet | B14: Tower | C14: Lantern | D14: Nautilus | E14: Vigil

Sheet More cores
A1: More cores — the second wing
A2: Four further cores in the same idiom (added 9 October 2026): keep the shells, swap the core. Each column links live to its sheet; the first four are on Four cores.
B4: PENDULUM — the ferry | C4: MOULT — the shed hull | D4: LIGHTHOUSE — the broadcast | E4: SUNDIVER — the homebody
A5: What replaces the shuttle bay | B5: A return engine. The ship swings out and home at 1 g forever; the shells are a terminal, not a colony. | C5: Nothing — that is the point. Each emptied shell is sealed and cast off; the hull that brakes at Proxima is half the hull that launched. | D5: A clock vault and a stern laser. The core broadcasts the crew's slower stream of time home for four centuries. | E5: A heat shield. The ship never leaves the Sun; it dives, and banks.
A6: Gravity | B6: Thrust, 1 g | C6: Spin | D6: Spin | E6: Spin (freefall in the dives)
A7: Physics status | B7: Known physics; the fare is the problem | C7: Known physics; a staging problem | D7: Known physics; nothing new flies at all | E7: Known physics; thermally heroic, temporally feeble
A8: Direction of travel | B8: Forward, round trip — the only core that comes home | C8: Forward | D8: Forward — and outward: it hands the stay-at-homes the voyage in slow motion | E8: Forward, barely
A9: Lead (live) | B9: =Pendulum!$B$20&" per cycle, per rider" -> 15.4 years per cycle, per rider | C9: =TEXT(Moult!$B$19,"0")&" years earlier at Proxima, with "&TEXT(Moult!$B$20,"0.0")&" days of lead" -> 90 years earlier at Proxima, with 10.5 days of lead | D9: ="400 ship-years air over "&TEXT(Lighthouse!$B$16,"0.0")&" Earth-years" -> 400 ship-years air over 404.2 Earth-years | E9: =TEXT(Sundiver!$B$19,"0")&" s banked in "&TEXT(Sundiver!$B$8,"0")&" years of diving" -> 180 s banked in 400 years of diving
A10: Who ages less | B10: The riders, one ticket at a time | C10: The crew — and the cast-off shells least of all | D10: The crew; Earth merely gets to watch | E10: The kettle
A11: The bill (live) | B11: =TEXT(Pendulum!$B$23,"#,##0")&" t of perfect-photon fuel per rider per cycle" -> 30,421,956,655 t of perfect-photon fuel per rider per cycle | C11: =TEXT(Moult!$B$38/1000,"#,##0")&" t of hull cast off — the speed is paid in shells, not fuel" -> 1,200,000,000 t of hull cast off — the speed is paid in shells, not fuel | D11: =TEXT(Lighthouse!$B$24,"#,##0")&" photons per second at Earth from a "&TEXT(Lighthouse!$B$6,"0")&" kW stern light" -> 2,774 photons per second at Earth from a 1 kW stern light | E11: ="A shield at ≥ "&TEXT(Sundiver!$B$20,"#,##0")&" K, forever" -> A shield at ≥ 2,046 K, forever
A12: The human problem | B12: The ferry crew can keep no friendship ashore: every workmate ages a cycle per cycle. | C12: Throwing away the rooms your grandparents lived in is Nautilus's nightmare — Moult and Nautilus cannot both be your culture. | D12: Celebrity without reply: the crew perform their lives for an audience whose answers arrive a childhood later. | E12: None. Nobody rides it; that is the verdict.
A13: Stacks with | B13: Lantern — a mouth at each terminal turns the ferry into a subway | C13: Vigil — each watch seals a shell and sheds it | D13: Every other core: any time ship should carry the Lighthouse as its black box | E13: The Greylock bench — a calibration source, not a ship
A14: Sheet | B14: Pendulum | C14: Moult | D14: Lighthouse | E14: Sundiver

Sheet Chrysalis
A1: Chrysalis as drawn — the baseline
A2: The Project Hyperion winner (i4is, 2025) as reported in press coverage of the entry; the team's own report may differ. Everything below is computed from the blue inputs, so change a number and the clocks, stresses and leads follow.
A5: Inputs, as reported
A6: Quantity | B6: Value | C6: Unit | D6: Notes / source
A7: Length | B7: 58 | C7: km | D7: holistic.news; Interesting Engineering (36 miles)
A8: Diameter | B8: 6 | C8: km | D8: holistic.news
A9: Mass (taken here as the dry, as-built mass) | B9: 2400000000 | C9: tonnes | D9: Indian Defence Review: 'over 2.4 billion tons'
A10: Capacity | B10: 2400 | C10: people | D10: Futura-Sciences; Interesting Engineering
A11: Steady-state population (births planned to hold this) | B11: 1500 | C11: people | D11: Futura-Sciences; holistic.news
A12: Distance to Proxima Centauri b | B12: 40000000000000 | C12: km | D12: itc.ua: '40 trillion kilometres' (Proxima is 4.25 ly = 4.02×10¹³ km)
A13: Journey time, Earth years | B13: 400 | C13: years | D13: itc.ua; holistic.news
A14: Gravity at the outer shell, from spin | B14: 1 | C14: g | D14: The ship rotates for gravity; 1 g at the rim is this sheet's assumption
A15: Nested layers around the core | B15: 5 | D15: Futura-Sciences ('five concentric layers')
A17: Assumptions (edit)
A18: Quantity | B18: Value | C18: Unit | D18: Notes / source
A19: Fusion exhaust velocity, as a fraction of c | B19: 0.0333 | C19: × c | D19: Daedalus-class D–³He exhaust ≈ 10,000 km/s. Chrysalis cites Daedalus-style fusion (Centauri Dreams).
A20: Life expectancy aboard | B20: 85 | C20: years | D20: Assumption
A21: Generation length | B21: 27 | C21: years | D21: Assumption
A22: Earliest launch | B22: 2125 | C22: year | D22: ≈75 years of Antarctic isolation + 20–25 years of construction, counted from now
A23: Boarding age used for the 'age at arrival' lines | B23: 25 | C23: years | D23: Assumption
A24: Tipler check: rim speed a time-machine cylinder would need | B24: 0.5 | C24: × c | D24: Tipler (1974): the surface must turn at more than about half the speed of light — and a finite cylinder needs negative energy anyway (Hawking 1992).
A25: Dust grain mass for the impact line | B25: 1 | C25: mg | D25: Assumption
A27: Geometry and cruise
A28: Quantity | B28: Value | C28: Unit | D28: Notes / source
A29: Radius | B29: =$B$8*1000/2 -> 3000 | C29: m
A30: Length | B30: =$B$7*1000 -> 58000 | C30: m
A31: Mass | B31: =$B$9*1000 -> 2400000000000 | C31: kg
A32: Distance | B32: =$B$12*1000 -> 4e+16 | C32: m
A33: Distance | B33: =$B$32/Constants!$B$12 -> 4.2280033 | C33: light-years
A34: Cruise speed (distance ÷ journey time) | B34: =$B$32/($B$13*Constants!$B$10) -> 3168808.8 | C34: m/s
A35: …in km/s | B35: =$B$34/1000 -> 3168.8088 | C35: km/s
A36: …as a fraction of c (β) | B36: =$B$34/Constants!$B$7 -> 0.010570008 | C36: × c | D36: About 1% of light speed
A37: Lorentz factor γ | B37: =1/SQRT(1-$B$36^2) -> 1.0000559
A39: Spin gravity and the clocks aboard
A40: Quantity | B40: Value | C40: Unit | D40: Notes / source
A41: Rim speed for the chosen gravity, √(g r) | B41: =SQRT($B$14*Constants!$B$8*$B$29) -> 171.52245 | C41: m/s
A42: Rotation period | B42: =2*PI()*$B$29/$B$41 -> 109.89556 | C42: s
A43: …in revolutions per minute | B43: =60/$B$42 -> 0.54597291 | C43: rpm
A44: Rim clock runs slow relative to the hub by v²/2c² | B44: =$B$41^2/(2*Constants!$B$7^2) -> 1.6367055e-13 | C44: fraction | D44: First-order term of 1 − 1/γ; exact to better than one part in 10¹³ here
A45: …as nanoseconds per day | B45: =$B$44*Constants!$B$11*1000000000 -> 14.141135 | C45: ns/day | D45: The spoken figure: 'about 14 ns/day'
A46: …in Greylocks (the project's Massachusetts machine) | B46: =$B$45/Constants!$B$39 -> 1.4191107 | C46: Greylocks | D46: 'A Greylock and a half, built into the floor plan'
A47: …in Jefferson towers (Pound–Rebka) | B47: =$B$45/Constants!$B$41 -> 66.666667 | C47: Jeffersons
A48: A whole lifetime at the rim lags the hub by | B48: =$B$44*$B$20*Constants!$B$10*1000 -> 0.43902922 | C48: ms | D48: Life expectancy × rate difference
A50: Hoop stress at the rim — a self-supporting thin shell carries σ = ρ v²
A51: Material | B51: Stress at the rim (MPa) | C51: Strength (MPa) | D51: Utilisation (stress ÷ strength)
A52: =Constants!$A$45 -> Structural steel (A36) | B52: =Constants!$B$45*$B$41^2/1000000 -> 230.94661 | C52: =Constants!$C$45 -> 250 | D52: =B52/C52 -> 0.92378643
A53: =Constants!$A$46 -> Aluminium 6061-T6 | B53: =Constants!$B$46*$B$41^2/1000000 -> 79.433865 | C53: =Constants!$C$46 -> 276 | D53: =B53/C53 -> 0.28780386
A54: =Constants!$A$47 -> Carbon-fibre laminate (unidirectional, fibre direction) | B54: =Constants!$B$47*$B$41^2/1000000 -> 47.07192 | C54: =Constants!$C$47 -> 1500 | D54: =B54/C54 -> 0.03138128
A55: =Constants!$A$48 -> Graphene (ideal single sheet) | B55: =Constants!$B$48*$B$41^2/1000000 -> 66.695027 | C55: =Constants!$C$48 -> 130000 | D55: =B55/C55 -> 0.00051303867
A56: σ = ρ v² is the stress in a spinning ring that holds up only itself; anything hung on the shell adds to it. At 1 g and 3 km radius, steel sits near its yield with nobody aboard — the spoken '≈230 MPa'. The stress is ρ g r, so it does not care how fast you spin: only the radius and the material matter.
A58: Tipler check — rim speed at the Tipler fraction of c | B58: =$B$24*Constants!$B$7 -> 149896229 | C58: m/s
A59: …hoop stress in steel at that speed, ρ v² | B59: =Constants!$B$45*$B$58^2/1000000 -> 176380703827100 | C59: MPa | D59: Compare 250 MPa yield. ρv² at near-c is the material's own rest-energy density: nothing holds.
A60: …÷ the strength of ideal graphene | B60: =$B$59/Constants!$C$48 -> 1.3567746e+09 | C60: × | D60: Even the strongest material known is short by this factor
A62: The journey as a time machine
A63: Quantity | B63: Value | C63: Unit | D63: Notes / source
A64: Ship time for the crossing, T√(1−β²) | B64: =$B$13*SQRT(1-$B$36^2) -> 399.97765 | C64: years
A65: Lead: Earth time − ship time | B65: =$B$13-$B$64 -> 0.022345639 | C65: years
A66: …in days (how much younger the passengers step off) | B66: =$B$65*365.25 -> 8.1617448 | C66: days | D66: The spoken figure: 'roughly a week'
A67: Earth's clock, slowed by the Sun's well at 1 AU: GM☉/(a c²) | B67: =Constants!$B$14/(Constants!$B$13*Constants!$B$7^2) -> 9.8706287e-09 | C67: fraction
A68: Earth's orbital speed 2π·AU/yr | B68: =2*PI()*Constants!$B$13/Constants!$B$10 -> 29785.254 | C68: m/s
A69: …slowing Earth's clock by v²/2c² | B69: =$B$68^2/(2*Constants!$B$7^2) -> 4.9355008e-09 | C69: fraction
A70: Earth's own well at the surface: GM⊕/(R⊕ c²) | B70: =Constants!$B$15/(Constants!$B$16*Constants!$B$7^2) -> 6.9535254e-10 | C70: fraction
A71: Total: Earth's clock vs a clock at rest far from the Sun (L_B) | B71: =$B$67+$B$69+$B$70 -> 1.5501482e-08 | C71: fraction | D71: Should read ≈1.550E-08, the IAU constant L_B relating TCB to TT
A72: Over the journey, Earth's clock loses | B72: =$B$71*$B$13*Constants!$B$10 -> 195.67583 | C72: s | D72: Climbing out of the Sun's well makes the ship older, not younger — it eats into the lead
A73: …in minutes | B73: =$B$72/60 -> 3.2612638 | C73: min | D73: The spoken figure: 'minus three minutes'
A74: Net lead on arrival | B74: =$B$66-$B$72/Constants!$B$11 -> 8.15948 | C74: days
A76: Fuel — read by the Nautilus and Vigil sheets
A77: Quantity | B77: Value | C77: Unit | D77: Notes / source
A78: Total Δv (accelerate to cruise, then brake) | B78: =2*$B$34 -> 6337617.6 | C78: m/s
A79: Mass ratio M₀/M₁ = exp(Δv/vₑ) | B79: =EXP($B$78/($B$19*Constants!$B$7)) -> 1.8867114 | C79: × | D79: Non-relativistic rocket equation is fine at 1% of c
A80: Fuel mass for the dry mass above | B80: =$B$31*($B$79-1) -> 2.1281075e+12 | C80: kg
A81: …in tonnes | B81: =$B$80/1000 -> 2.1281075e+09 | C81: tonnes | D81: Nearly a second ship's worth of deuterium and helium-3
A83: People
A84: Quantity | B84: Value | C84: Unit | D84: Notes / source
A85: Births per year to hold the population | B85: =$B$11/$B$20 -> 17.647059 | C85: per year
A86: Generations over the journey | B86: =$B$13/$B$21 -> 14.814815
A87: People who will ever live aboard (approx.) | B87: =$B$11*(1+$B$13/$B$20) -> 8558.8235 | C87: people | D87: Founding population plus replacements
A89: What the ship ploughs through
A90: Quantity | B90: Value | C90: Unit | D90: Notes / source
A91: Hydrogen swept per m² of nose over the trip, n m_p d | B91: =Constants!$B$29*1000000*Constants!$B$20*$B$32 -> 6.6904877e-05 | C91: kg/m²
A92: Nose area π r² | B92: =PI()*$B$29^2 -> 28274334 | C92: m²
A93: Hydrogen swept by the whole nose | B93: =$B$91*$B$92 -> 1891.6908 | C93: kg | D93: Two tonnes in four centuries: 'mining en route' is a rounding error
A94: Dust swept by the nose | B94: =Constants!$B$30*$B$93 -> 18.916908 | C94: kg
A95: Kinetic energy of one dust grain at cruise, ½mv² | B95: =0.5*$B$25*0.000001*$B$34^2 -> 5020674.5 | C95: J
A96: …in kilograms of TNT | B96: =$B$95/Constants!$B$25 -> 1.19997 | C96: kg TNT | D96: A milligram grain at 1% of c hits like a stick of dynamite; this is why the ship needs a bow shield even at Chrysalis speed

Sheet Lead table
A1: Lead table — how much younger the ship arrives
A2: Coast rows: constant cruise speed (acceleration phases ignored). Torch rows: constant proper acceleration to the midpoint, flip, brake. Legs = 2 for there-and-back. Lead = Earth time − ship time. Mass ratio uses the relativistic rocket equation M₀/M₁ = exp(φ·c/vₑ) per boost, with one accelerate and one brake per leg. Blue = input, green = link, black = formula. Rows 10–11 are yours to play with.
A4: Ship | B4: Mode | C4: Distance one way (ly) | D4: Legs | E4: Cruise speed β (coast) | F4: Proper accel. (g) (torch) | G4: Exhaust speed βₑ (× c) | H4: c/a (years, torch) | I4: x = a·(d/2)/c² (torch) | J4: Rapidity φ per boost | K4: Peak speed β_max | L4: Peak γ | M4: Ship time per leg (yr) | N4: Earth time per leg (yr) | O4: Ship time total (yr) | P4: Earth time total (yr) | Q4: Lead (yr) | R4: Lead, readable | S4: Boosts | T4: Mass ratio M₀/M₁ | U4: Fuel per tonne of ship (t) | V4: Final separation from Earth (ly) | W4: Light-time Earth↔ship at the end (yr)
A5: Chrysalis as drawn (~1% c) | B5: coast | C5: =Chrysalis!$B$33 -> 4.2280033 | D5: 1 | E5: =Chrysalis!$B$36 -> 0.010570008 | G5: =Chrysalis!$B$19 -> 0.0333 | H5: =IF(B5="torch",Constants!$B$7/(F5*Constants!$B$8)/Constants!$B$10,"") | I5: =IF(B5="torch",F5*Constants!$B$8*(C5*Constants!$B$12/2)/Constants!$B$7^2,"") | J5: =IF(B5="torch",ACOSH(1+I5),ATANH(E5)) -> 0.010570402 | K5: =TANH(J5) -> 0.010570008 | L5: =COSH(J5) -> 1.0000559 | M5: =IF(B5="torch",2*H5*J5,C5/E5/L5) -> 399.97765 | N5: =IF(B5="torch",2*H5*SINH(J5),C5/E5) -> 400 | O5: =D5*M5 -> 399.97765 | P5: =D5*N5 -> 400 | Q5: =P5-O5 -> 0.022345639 | R5: =IF(Q5<1/12,TEXT(Q5*365.25,"0.0")&" days",IF(Q5<1,TEXT(Q5*12,"0.0")&" months",IF(Q5<10,TEXT(Q5,"0.0")&" years",TEXT(Q5,"#,##0")&" years"))) -> 8.2 days | S5: =2*D5 -> 2 | T5: =EXP(S5*J5/G5) -> 1.8867561 | U5: =T5-1 -> 0.88675605 | V5: =IF(D5=1,C5,0) -> 4.2280033 | W5: =V5*Constants!$B$12/Constants!$B$7/Constants!$B$10 -> 4.2280033
A6: Fusion pushed to Daedalus speed (0.1 c) | B6: coast | C6: 4.2465 | D6: 1 | E6: 0.1 | G6: 0.0333 | H6: =IF(B6="torch",Constants!$B$7/(F6*Constants!$B$8)/Constants!$B$10,"") | I6: =IF(B6="torch",F6*Constants!$B$8*(C6*Constants!$B$12/2)/Constants!$B$7^2,"") | J6: =IF(B6="torch",ACOSH(1+I6),ATANH(E6)) -> 0.10033535 | K6: =TANH(J6) -> 0.1 | L6: =COSH(J6) -> 1.0050378 | M6: =IF(B6="torch",2*H6*J6,C6/E6/L6) -> 42.252142 | N6: =IF(B6="torch",2*H6*SINH(J6),C6/E6) -> 42.465 | O6: =D6*M6 -> 42.252142 | P6: =D6*N6 -> 42.465 | Q6: =P6-O6 -> 0.21285848 | R6: =IF(Q6<1/12,TEXT(Q6*365.25,"0.0")&" days",IF(Q6<1,TEXT(Q6*12,"0.0")&" months",IF(Q6<10,TEXT(Q6,"0.0")&" years",TEXT(Q6,"#,##0")&" years"))) -> 2.6 months | S6: =2*D6 -> 2 | T6: =EXP(S6*J6/G6) -> 414.11637 | U6: =T6-1 -> 413.11637 | V6: =IF(D6=1,C6,0) -> 4.2465 | W6: =V6*Constants!$B$12/Constants!$B$7/Constants!$B$10 -> 4.2465
A7: 1 g torch to Proxima | B7: torch | C7: 4.2465 | D7: 1 | F7: 1 | G7: 1 | H7: =IF(B7="torch",Constants!$B$7/(F7*Constants!$B$8)/Constants!$B$10,"") -> 0.96871508 | I7: =IF(B7="torch",F7*Constants!$B$8*(C7*Constants!$B$12/2)/Constants!$B$7^2,"") -> 2.1918209 | J7: =IF(B7="torch",ACOSH(1+I7),ATANH(E7)) -> 1.8282435 | K7: =TANH(J7) -> 0.94965395 | L7: =COSH(J7) -> 3.1918209 | M7: =IF(B7="torch",2*H7*J7,C7/E7/L7) -> 3.542094 | N7: =IF(B7="torch",2*H7*SINH(J7),C7/E7) -> 5.8725937 | O7: =D7*M7 -> 3.542094 | P7: =D7*N7 -> 5.8725937 | Q7: =P7-O7 -> 2.3304996 | R7: =IF(Q7<1/12,TEXT(Q7*365.25,"0.0")&" days",IF(Q7<1,TEXT(Q7*12,"0.0")&" months",IF(Q7<10,TEXT(Q7,"0.0")&" years",TEXT(Q7,"#,##0")&" years"))) -> 2.3 years | S7: =2*D7 -> 2 | T7: =EXP(S7*J7/G7) -> 38.725061 | U7: =T7-1 -> 37.725061 | V7: =IF(D7=1,C7,0) -> 4.2465 | W7: =V7*Constants!$B$12/Constants!$B$7/Constants!$B$10 -> 4.2465
A8: 1 g, 1,000 ly and back | B8: torch | C8: 1000 | D8: 2 | F8: 1 | G8: 1 | H8: =IF(B8="torch",Constants!$B$7/(F8*Constants!$B$8)/Constants!$B$10,"") -> 0.96871508 | I8: =IF(B8="torch",F8*Constants!$B$8*(C8*Constants!$B$12/2)/Constants!$B$7^2,"") -> 516.14764 | J8: =IF(B8="torch",ACOSH(1+I8),ATANH(E8)) -> 6.9414746 | K8: =TANH(J8) -> 0.99999813 | L8: =COSH(J8) -> 517.14764 | M8: =IF(B8="torch",2*H8*J8,C8/E8/L8) -> 13.448622 | N8: =IF(B8="torch",2*H8*SINH(J8),C8/E8) -> 1001.9356 | O8: =D8*M8 -> 26.897245 | P8: =D8*N8 -> 2003.8711 | Q8: =P8-O8 -> 1976.9739 | R8: =IF(Q8<1/12,TEXT(Q8*365.25,"0.0")&" days",IF(Q8<1,TEXT(Q8*12,"0.0")&" months",IF(Q8<10,TEXT(Q8,"0.0")&" years",TEXT(Q8,"#,##0")&" years"))) -> 1,977 years | S8: =2*D8 -> 4 | T8: =EXP(S8*J8/G8) -> 1.1443965e+12 | U8: =T8-1 -> 1.1443965e+12 | V8: =IF(D8=1,C8,0) -> 0 | W8: =V8*Constants!$B$12/Constants!$B$7/Constants!$B$10 -> 0
A9: 1 g to the galactic centre | B9: torch | C9: 26000 | D9: 1 | F9: 1 | G9: 1 | H9: =IF(B9="torch",Constants!$B$7/(F9*Constants!$B$8)/Constants!$B$10,"") -> 0.96871508 | I9: =IF(B9="torch",F9*Constants!$B$8*(C9*Constants!$B$12/2)/Constants!$B$7^2,"") -> 13419.839 | J9: =IF(B9="torch",ACOSH(1+I9),ATANH(E9)) -> 10.197711 | K9: =TANH(J9) -> 1 | L9: =COSH(J9) -> 13420.839 | M9: =IF(B9="torch",2*H9*J9,C9/E9/L9) -> 19.757353 | N9: =IF(B9="torch",2*H9*SINH(J9),C9/E9) -> 26001.937 | O9: =D9*M9 -> 19.757353 | P9: =D9*N9 -> 26001.937 | Q9: =P9-O9 -> 25982.18 | R9: =IF(Q9<1/12,TEXT(Q9*365.25,"0.0")&" days",IF(Q9<1,TEXT(Q9*12,"0.0")&" months",IF(Q9<10,TEXT(Q9,"0.0")&" years",TEXT(Q9,"#,##0")&" years"))) -> 25,982 years | S9: =2*D9 -> 2 | T9: =EXP(S9*J9/G9) -> 7.2047563e+08 | U9: =T9-1 -> 7.2047563e+08 | V9: =IF(D9=1,C9,0) -> 26000 | W9: =V9*Constants!$B$12/Constants!$B$7/Constants!$B$10 -> 26000
A10: Your ship A (torch) | B10: torch | C10: 100 | D10: 1 | F10: 0.5 | G10: 1 | H10: =IF(B10="torch",Constants!$B$7/(F10*Constants!$B$8)/Constants!$B$10,"") -> 1.9374302 | I10: =IF(B10="torch",F10*Constants!$B$8*(C10*Constants!$B$12/2)/Constants!$B$7^2,"") -> 25.807382 | J10: =IF(B10="torch",ACOSH(1+I10),ATANH(E10)) -> 3.9814764 | K10: =TANH(J10) -> 0.99930399 | L10: =COSH(J10) -> 26.807382 | M10: =IF(B10="torch",2*H10*J10,C10/E10/L10) -> 15.427665 | N10: =IF(B10="torch",2*H10*SINH(J10),C10/E10) -> 103.80256 | O10: =D10*M10 -> 15.427665 | P10: =D10*N10 -> 103.80256 | Q10: =P10-O10 -> 88.374898 | R10: =IF(Q10<1/12,TEXT(Q10*365.25,"0.0")&" days",IF(Q10<1,TEXT(Q10*12,"0.0")&" months",IF(Q10<10,TEXT(Q10,"0.0")&" years",TEXT(Q10,"#,##0")&" years"))) -> 88 years | S10: =2*D10 -> 2 | T10: =EXP(S10*J10/G10) -> 2872.5425 | U10: =T10-1 -> 2871.5425 | V10: =IF(D10=1,C10,0) -> 100 | W10: =V10*Constants!$B$12/Constants!$B$7/Constants!$B$10 -> 100
A11: Your ship B (coast) | B11: coast | C11: 4.2465 | D11: 1 | E11: 0.5 | G11: 1 | H11: =IF(B11="torch",Constants!$B$7/(F11*Constants!$B$8)/Constants!$B$10,"") | I11: =IF(B11="torch",F11*Constants!$B$8*(C11*Constants!$B$12/2)/Constants!$B$7^2,"") | J11: =IF(B11="torch",ACOSH(1+I11),ATANH(E11)) -> 0.54930614 | K11: =TANH(J11) -> 0.5 | L11: =COSH(J11) -> 1.1547005 | M11: =IF(B11="torch",2*H11*J11,C11/E11/L11) -> 7.3551538 | N11: =IF(B11="torch",2*H11*SINH(J11),C11/E11) -> 8.493 | O11: =D11*M11 -> 7.3551538 | P11: =D11*N11 -> 8.493 | Q11: =P11-O11 -> 1.1378462 | R11: =IF(Q11<1/12,TEXT(Q11*365.25,"0.0")&" days",IF(Q11<1,TEXT(Q11*12,"0.0")&" months",IF(Q11<10,TEXT(Q11,"0.0")&" years",TEXT(Q11,"#,##0")&" years"))) -> 1.1 years | S11: =2*D11 -> 2 | T11: =EXP(S11*J11/G11) -> 3 | U11: =T11-1 -> 2 | V11: =IF(D11=1,C11,0) -> 4.2465 | W11: =V11*Constants!$B$12/Constants!$B$7/Constants!$B$10 -> 4.2465
A13: Formulas: torch — x = a(d/2)/c², φ = acosh(1+x), ship time per leg τ = 2(c/a)φ, Earth time per leg t = 2(c/a)sinh φ, β_max = tanh φ, γ_max = 1+x. Coast — φ = atanh β, t = d/v, τ = t/γ. Mass ratio per boost = exp(φ c/vₑ); boosts = 2 per leg.
A14: βₑ = 1 is a perfect photon rocket (antimatter, perfectly collimated, no waste heat) — the floor on the fuel bill, not an engine anyone has. βₑ = 0.0333 is Daedalus-class fusion.
A15: The Chrysalis row (as drawn) reads its speed, distance and exhaust from the Chrysalis sheet. 'Legs = 2' leaves the ship back at Earth, which is what turns a Lantern door into a closed timelike curve (see the Lantern sheet).
A17: A 1 g ship, one way with braking: times vs distance (chart data)
A18: One-way distance (ly) | B18: Ship time (yr) | C18: Earth time (yr) | D18: Lead (yr)
A19: 1 | B19: =2*(Constants!$B$7/Constants!$B$8/Constants!$B$10)*ACOSH(1+Constants!$B$8*(A19*Constants!$B$12/2)/Constants!$B$7^2) -> 1.8923438 | C19: =2*(Constants!$B$7/Constants!$B$8/Constants!$B$10)*SINH(ACOSH(1+Constants!$B$8*(A19*Constants!$B$12/2)/Constants!$B$7^2)) -> 2.2079086 | D19: =C19-B19 -> 0.3155648
A20: 2 | B20: =2*(Constants!$B$7/Constants!$B$8/Constants!$B$10)*ACOSH(1+Constants!$B$8*(A20*Constants!$B$12/2)/Constants!$B$7^2) -> 2.5872559 | C20: =2*(Constants!$B$7/Constants!$B$8/Constants!$B$10)*SINH(ACOSH(1+Constants!$B$8*(A20*Constants!$B$12/2)/Constants!$B$7^2)) -> 3.4277866 | D20: =C20-B20 -> 0.84053062
A21: 4.2465 | B21: =2*(Constants!$B$7/Constants!$B$8/Constants!$B$10)*ACOSH(1+Constants!$B$8*(A21*Constants!$B$12/2)/Constants!$B$7^2) -> 3.542094 | C21: =2*(Constants!$B$7/Constants!$B$8/Constants!$B$10)*SINH(ACOSH(1+Constants!$B$8*(A21*Constants!$B$12/2)/Constants!$B$7^2)) -> 5.8725937 | D21: =C21-B21 -> 2.3304996
A22: 10 | B22: =2*(Constants!$B$7/Constants!$B$8/Constants!$B$10)*ACOSH(1+Constants!$B$8*(A22*Constants!$B$12/2)/Constants!$B$7^2) -> 4.852899 | C22: =2*(Constants!$B$7/Constants!$B$8/Constants!$B$10)*SINH(ACOSH(1+Constants!$B$8*(A22*Constants!$B$12/2)/Constants!$B$7^2)) -> 11.77916 | D22: =C22-B22 -> 6.9262607
A23: 30 | B23: =2*(Constants!$B$7/Constants!$B$8/Constants!$B$10)*ACOSH(1+Constants!$B$8*(A23*Constants!$B$12/2)/Constants!$B$7^2) -> 6.7706251 | C23: =2*(Constants!$B$7/Constants!$B$8/Constants!$B$10)*SINH(ACOSH(1+Constants!$B$8*(A23*Constants!$B$12/2)/Constants!$B$7^2)) -> 31.878611 | D23: =C23-B23 -> 25.107985
A24: 100 | B24: =2*(Constants!$B$7/Constants!$B$8/Constants!$B$10)*ACOSH(1+Constants!$B$8*(A24*Constants!$B$12/2)/Constants!$B$7^2) -> 9.0207787 | C24: =2*(Constants!$B$7/Constants!$B$8/Constants!$B$10)*SINH(ACOSH(1+Constants!$B$8*(A24*Constants!$B$12/2)/Constants!$B$7^2)) -> 101.91902 | D24: =C24-B24 -> 92.898238
A25: 300 | B25: =2*(Constants!$B$7/Constants!$B$8/Constants!$B$10)*ACOSH(1+Constants!$B$8*(A25*Constants!$B$12/2)/Constants!$B$7^2) -> 11.124713 | C25: =2*(Constants!$B$7/Constants!$B$8/Constants!$B$10)*SINH(ACOSH(1+Constants!$B$8*(A25*Constants!$B$12/2)/Constants!$B$7^2)) -> 301.93121 | D25: =C25-B25 -> 290.8065
A26: 1000 | B26: =2*(Constants!$B$7/Constants!$B$8/Constants!$B$10)*ACOSH(1+Constants!$B$8*(A26*Constants!$B$12/2)/Constants!$B$7^2) -> 13.448622 | C26: =2*(Constants!$B$7/Constants!$B$8/Constants!$B$10)*SINH(ACOSH(1+Constants!$B$8*(A26*Constants!$B$12/2)/Constants!$B$7^2)) -> 1001.9356 | D26: =C26-B26 -> 988.48693
A27: 3000 | B27: =2*(Constants!$B$7/Constants!$B$8/Constants!$B$10)*ACOSH(1+Constants!$B$8*(A27*Constants!$B$12/2)/Constants!$B$7^2) -> 15.574609 | C27: =2*(Constants!$B$7/Constants!$B$8/Constants!$B$10)*SINH(ACOSH(1+Constants!$B$8*(A27*Constants!$B$12/2)/Constants!$B$7^2)) -> 3001.9368 | D27: =C27-B27 -> 2986.3622
A28: 10000 | B28: =2*(Constants!$B$7/Constants!$B$8/Constants!$B$10)*ACOSH(1+Constants!$B$8*(A28*Constants!$B$12/2)/Constants!$B$7^2) -> 17.906347 | C28: =2*(Constants!$B$7/Constants!$B$8/Constants!$B$10)*SINH(ACOSH(1+Constants!$B$8*(A28*Constants!$B$12/2)/Constants!$B$7^2)) -> 10001.937 | D28: =C28-B28 -> 9984.0309
A29: 26000 | B29: =2*(Constants!$B$7/Constants!$B$8/Constants!$B$10)*ACOSH(1+Constants!$B$8*(A29*Constants!$B$12/2)/Constants!$B$7^2) -> 19.757353 | C29: =2*(Constants!$B$7/Constants!$B$8/Constants!$B$10)*SINH(ACOSH(1+Constants!$B$8*(A29*Constants!$B$12/2)/Constants!$B$7^2)) -> 26001.937 | D29: =C29-B29 -> 25982.18
A30: 100000 | B30: =2*(Constants!$B$7/Constants!$B$8/Constants!$B$10)*ACOSH(1+Constants!$B$8*(A30*Constants!$B$12/2)/Constants!$B$7^2) -> 22.367107 | C30: =2*(Constants!$B$7/Constants!$B$8/Constants!$B$10)*SINH(ACOSH(1+Constants!$B$8*(A30*Constants!$B$12/2)/Constants!$B$7^2)) -> 100001.94 | D30: =C30-B30 -> 99979.57

Sheet Tower
A1: Tower — the honest one: the core is the engine
A2: A time ship in known physics is a dilation ship, and a dilation ship thrusts for most of the trip. Spin gravity gives way to thrust gravity: 'down' is aft, the nested shells become stacked floors, and the ship is a 58-km-tall building standing on its exhaust. Pick a ship from the Lead table in the dropdown; everything below follows it.
A5: Choose the ship (dropdown) and the assumptions
A6: Quantity | B6: Value | C6: Unit | D6: Notes / source
A7: Ship (any name from the Lead table) | B7: 1 g torch to Proxima | D7: Dropdown — rows of the Lead table
A8: Floor pitch | B8: 5 | C8: m | D8: Assumption
A9: Express-lift speed | B9: 10 | C9: m/s | D9: Fast skyscraper lifts do ~10 m/s
A10: Ice: latent heat of sublimation | B10: 2830000 | C10: J/kg | D10: ≈2.83 MJ/kg; ignores sensible heating from storage temperature, so the ice figures are slightly generous to the ship
A11: Ship dry mass | B11: =Chrysalis!$B$31 -> 2400000000000 | C11: kg | D11: From the Chrysalis sheet
A12: Nose / footprint radius | B12: =Chrysalis!$B$29 -> 3000 | C12: m | D12: From the Chrysalis sheet
A13: Height of the tower (the ship's length) | B13: =Chrysalis!$B$30 -> 58000 | C13: m | D13: From the Chrysalis sheet
A14: Travellers aboard | B14: =Chrysalis!$B$10 -> 2400 | C14: people | D14: Chrysalis capacity; nobody is born en route
A15: Launch year | B15: =Chrysalis!$B$22 -> 2125 | C15: year
A16: Boarding age | B16: =Chrysalis!$B$23 -> 25 | C16: years
A18: Pulled from the Lead table for the chosen ship
A19: Quantity | B19: Value | C19: Unit | D19: Notes / source
A20: Row index in the Lead table | B20: =MATCH($B$7,'Lead table'!$A$5:$A$11,0) -> 3
A21: Mode | B21: =INDEX('Lead table'!$B$5:$B$11,$B$20) -> torch
A22: Proper acceleration | B22: =INDEX('Lead table'!$F$5:$F$11,$B$20) -> 1 | C22: g | D22: Blank for a coast row: the thrust-gravity block below then reads zero
A23: Distance one way | B23: =INDEX('Lead table'!$C$5:$C$11,$B$20) -> 4.2465 | C23: ly
A24: Legs | B24: =INDEX('Lead table'!$D$5:$D$11,$B$20) -> 1
A25: Rapidity per boost φ | B25: =INDEX('Lead table'!$J$5:$J$11,$B$20) -> 1.8282435
A26: Peak speed β_max | B26: =INDEX('Lead table'!$K$5:$K$11,$B$20) -> 0.94965395 | C26: × c
A27: Peak γ | B27: =INDEX('Lead table'!$L$5:$L$11,$B$20) -> 3.1918209
A28: Ship time, total | B28: =INDEX('Lead table'!$O$5:$O$11,$B$20) -> 3.542094 | C28: years
A29: Earth time, total | B29: =INDEX('Lead table'!$P$5:$P$11,$B$20) -> 5.8725937 | C29: years
A30: Lead | B30: =INDEX('Lead table'!$Q$5:$Q$11,$B$20) -> 2.3304996 | C30: years
A31: Lead, readable | B31: =INDEX('Lead table'!$R$5:$R$11,$B$20) -> 2.3 years
A32: Mass ratio M₀/M₁ | B32: =INDEX('Lead table'!$T$5:$T$11,$B$20) -> 38.725061 | C32: ×
A34: Thrust gravity — the structure is cheap on paper
A35: Quantity | B35: Value | C35: Unit | D35: Notes / source
A36: Acceleration | B36: =IF(ISNUMBER($B$22),$B$22*Constants!$B$8,0) -> 9.80665 | C36: m/s²
A37: Ship's weight under thrust, M·a (= the thrust at dry mass) | B37: =$B$11*$B$36 -> 23535960000000 | C37: N | D37: The spoken figure: 2.4×10¹³ N at 1 g
A38: Footprint π r² | B38: =PI()*$B$12^2 -> 28274334 | C38: m²
A39: Pressure on the base | B39: =$B$37/$B$38 -> 832414.31 | C39: Pa
A40: …in MPa | B40: =$B$39/1000000 -> 0.83241431 | C40: MPa | D40: Under 1 MPa: the spoken 'less than a bike tyre'
A41: …in road-bike tyres | B41: =$B$40/Constants!$B$31 -> 1.1891633 | C41: tyres
A42: …as a fraction of steel's yield strength | B42: =$B$40/Constants!$C$45 -> 0.0033296572 | D42: If the whole base were a solid steel plate; the hard part is funnelling the thrust into one engine, not holding the building up
A44: The engine — a perfect photon rocket (the floor on the bill)
A45: Quantity | B45: Value | C45: Unit | D45: Notes / source
A46: Thrust needed at departure, fully fuelled: M₀·a | B46: =$B$11*$B$32*$B$36 -> 911431479124118 | C46: N
A47: Radiated power at dry mass, F·c | B47: =$B$37*Constants!$B$7 -> 7.0559033e+21 | C47: W | D47: The spoken figure: 7×10²¹ W
A48: Radiated power at departure, fully fuelled | B48: =$B$46*Constants!$B$7 -> 2.7324028e+23 | C48: W
A49: Dry-mass power as a fraction of the Sun | B49: =$B$47/Constants!$B$19 -> 1.8432349e-05
A50: …i.e. one Sun per | B50: =Constants!$B$19/$B$47 -> 54252.444 | C50: ships | D50: The spoken 'a fifty-thousandth of a Sun'
A51: At departure, one Sun per | B51: =Constants!$B$19/$B$48 -> 1400.9647 | C51: ships
A52: Fuel mass for the chosen ship, (M₀/M₁ − 1) × dry mass | B52: =($B$32-1)*$B$11/1000 -> 9.0540146e+10 | C52: tonnes | D52: '~40 tonnes of fuel per tonne of ship' for the Proxima torch
A54: Living in a tower
A55: Quantity | B55: Value | C55: Unit | D55: Notes / source
A56: Floors, if the whole length were floors | B56: =$B$13/$B$8 -> 11600 | C56: floors
A57: Express lift, stern to prow | B57: =$B$13/$B$9/60 -> 96.666667 | C57: minutes
A58: Clock gradient, prow vs stern: a·L/c² (equivalence principle) | B58: =$B$36*$B$13/Constants!$B$7^2 -> 6.3285944e-12 | C58: fraction | D58: Pound–Rebka scaled up: the prow ages faster than the stern
A59: …as microseconds per day | B59: =$B$58*Constants!$B$11*1000000 -> 0.54679056 | C59: µs/day
A60: …in Greylocks | B60: =$B$58/Constants!$B$38 -> 54.87228 | C60: Greylocks
A61: …in Jefferson towers | B61: =$B$58/Constants!$B$40 -> 2577.7778 | C61: Jeffersons
A62: Over the whole trip, the prow runs ahead of the stern by | B62: =$B$58*$B$28*Constants!$B$10*1000 -> 0.7074102 | C62: ms | D62: Only while thrusting; a coast row gives zero
A64: The prow — interstellar hydrogen as a particle beam (and why a glacier won't do)
A65: Quantity | B65: Value | C65: Unit | D65: Notes / source
A66: Interstellar hydrogen density | B66: =Constants!$B$29 -> 1 | C66: cm⁻³ | D66: Constants sheet (edit there)
A67: Prow radius facing the stream | B67: =$B$12 -> 3000 | C67: m | D67: Defaults to the ship's radius (the tower's top face). Overwrite with a smaller number to try a needle prow.
A68: Prow area π r² | B68: =PI()*$B$67^2 -> 28274334 | C68: m²
A69: Tungsten melting point | B69: 3695 | C69: K | D69: For the refractory-bow check
A70: Carbon sublimation point | B70: 3915 | C70: K | D70: At 1 atm; lower in vacuum
A71: Proton kinetic energy at peak speed, (γ−1) m_p c² | B71: =($B$27-1)*Constants!$B$22/Constants!$B$21/1000000000 -> 2.0565244 | C71: GeV | D71: The spoken '2-GeV protons' at 0.95 c
A72: Peak energy flux on the nose, γ n β c (γ−1) m_p c² | B72: =$B$27*$B$66*1000000*$B$26*Constants!$B$7*($B$27-1)*Constants!$B$22 -> 299411.77 | C72: W/m² | D72: Density in the ship's frame is γn (length contraction). The spoken '~100 kW/m²' left out that γ: the right figure is nearer 300 kW/m².
A73: …in kW/m² | B73: =$B$72/1000 -> 299.41177 | C73: kW/m²
A74: Black-body temperature that re-radiates the peak flux | B74: =($B$72/Constants!$B$24)^0.25 -> 1515.8781 | C74: K | D74: Ice cannot sit at this temperature, so an ice prow is spent, not cooled; a refractory plate glowing at this temperature radiates the load back out
A75: Refractory bow check | B75: =IF($B$74<$B$69,"A tungsten or carbon bow plate glowing at "&TEXT($B$74,"#,##0")&" K can re-radiate the peak load","Even tungsten melts at this flux: needs a magnetic deflector or a needle prow") -> A tungsten or carbon bow plate glowing at 1,516 K can re-radiate the peak load | D75: 2-GeV protons shower through about a metre of material (nuclear interaction length in water ≈ 0.83 m), so the bow is a thick plate heated throughout, not a skin — and the crew need a radiation shield behind it
A76: Energy deposited per m² per leg, n m_p c² ∫(γ−1)dx | B76: =IF($B$21="torch",$B$66*1000000*Constants!$B$20*$B$36*($B$23*Constants!$B$12)^2/4,$B$66*1000000*Constants!$B$20*Constants!$B$7^2*($B$27-1)*$B$23*Constants!$B$12) -> 6.6186599e+12 | C76: J/m² | D76: Torch: γ−1 = ax/c² on each half, so the integral is a d²/4c². Coast: (γ−1) is constant.
A77: …for all legs | B77: =$B$76*$B$24 -> 6.6186599e+12 | C77: J/m²
A78: Energy into the whole prow | B78: =$B$77*$B$68 -> 1.871382e+20 | C78: J
A79: Ice spent if every joule sublimates ice (the sacrificial-glacier bound) | B79: =$B$78/$B$10/1000 -> 6.6126572e+10 | C79: tonnes
A80: …in gigatonnes | B80: =$B$79/1000000000 -> 66.126572 | C80: Gt | D80: The spoken '~30 Mt of ice' was wrong by three orders of magnitude: a full-width ice prow at n = 1 cm⁻³ needs tens of gigatonnes
A81: …in ships' worth of mass | B81: =$B$79*1000/$B$11 -> 27.552739 | C81: ships | D81: So the prow cannot be a glacier: it must be a narrow needle, a refractory radiator (above), a magnetic deflector, or all three
A82: …as a slab of ice over the prow | B82: =$B$79*1000/917/$B$68/1000 -> 2.5504352 | C82: km thick | D82: Ice density 917 kg/m³
A83: …per traveller | B83: =$B$79/$B$14 -> 27552739 | C83: tonnes each
A84: Hydrogen mass swept per m² over all legs | B84: =$B$66*1000000*Constants!$B$20*$B$23*Constants!$B$12*$B$24 -> 6.7197572e-05 | C84: kg/m² | D84: Tiny — it is the energy, not the mass, that erodes the prow
A86: The crew are the travellers
A87: Quantity | B87: Value | C87: Unit | D87: Notes / source
A88: Years aboard (ship time) | B88: =$B$28 -> 3.542094 | C88: years
A89: Age at arrival, boarding at the boarding age | B89: =$B$16+$B$28 -> 28.542094 | C89: years
A90: Earth calendar on arrival | B90: =$B$15+$B$29 -> 2130.8726 | C90: year
A91: How far the crew have outrun Earth's calendar | B91: =$B$31 -> 2.3 years | D91: No mission control waits at the far end: the ship carries its own Earth

Sheet Lantern
A1: Lantern — the door: the core is a wormhole mouth
A2: The one backward route general relativity allows on paper (Morris, Thorne & Yurtsever 1988): hold a throat open with negative energy, leave one mouth at the Earth–Moon L1 yard where the ship is assembled, carry the other in the hub where Chrysalis keeps its comms. The throat keeps the two mouths in step by proper time, so every day of lead the ship banks becomes a day the door opens into the past.
A5: Inputs
A6: Quantity | B6: Value | C6: Unit | D6: Notes / source
A7: Throat radius (a person-sized door) | B7: 2 | C7: m | D7: Assumption
A8: Ship carrying the far mouth (dropdown) | B8: 1 g torch to Proxima | D8: Any name from the Lead table
A9: Home mouth stays at | B9: Earth–Moon L1 assembly yard | D9: Where Chrysalis is built (Interesting Engineering)
A11: The bill nobody can pay
A12: Quantity | B12: Value | C12: Unit | D12: Notes / source
A13: Negative mass needed, of order c²·r/G | B13: =Constants!$B$7^2*$B$7/Constants!$B$9 -> 2.6931818e+27 | C13: kg (negative) | D13: Order-of-magnitude for a Morris–Thorne throat: |M| ~ c² r / G. Quantum field theory allows negative energy only in tiny, fleeting amounts.
A14: …in Jupiter masses | B14: =$B$13/Constants!$B$18 -> 1.4188083 | C14: Jupiters | D14: The spoken 'a Jupiter per metre of throat'
A15: …in Earth masses | B15: =$B$13/Constants!$B$17 -> 450.95306 | C15: Earths
A16: Per metre of throat radius | B16: =Constants!$B$7^2/Constants!$B$9/Constants!$B$18 -> 0.70940413 | C16: Jupiters/m
A18: How deep the door goes — for the chosen ship
A19: Quantity | B19: Value | C19: Unit | D19: Notes / source
A20: Row index in the Lead table | B20: =MATCH($B$8,'Lead table'!$A$5:$A$11,0) -> 3
A21: Lead banked by the ship (Earth time − ship time) | B21: =INDEX('Lead table'!$Q$5:$Q$11,$B$20) -> 2.3304996 | C21: years
A22: …readable | B22: =INDEX('Lead table'!$R$5:$R$11,$B$20) -> 2.3 years | D22: Step into the ship's mouth and you come out of the home mouth this much earlier in Earth's calendar — after the ship left, never before
A23: Separation of the mouths at the end | B23: =INDEX('Lead table'!$V$5:$V$11,$B$20) -> 4.2465 | C23: ly
A24: Light-time between the mouths through ordinary space | B24: =INDEX('Lead table'!$W$5:$W$11,$B$20) -> 4.2465 | C24: years | D24: A radio message takes this long; the door takes no time at all
A25: Safety margin: light-time − lead | B25: =$B$24-$B$21 -> 1.9160004 | C25: years | D25: Positive: no closed timelike curve can form. Negative: the door plus a light-speed trip back closes a loop in time.
A26: Chronology status | B26: =IF($B$25>0,"No closed timelike curve: the door is safe","Closed timelike curve forms: chronology-protection territory") -> No closed timelike curve: the door is safe | D26: Keeping the lag shorter than the light-time between the mouths is the built-in speed limit (Morris–Thorne–Yurtsever 1988; Hawking 1992)
A27: Deepest safe door for this separation | B27: =$B$24 -> 4.2465 | C27: years | D27: Equal to the light-time; any deeper and a loop closes
A29: All seven ships at once
A30: Ship | B30: Door depth (yr) | C30: Light-time (yr) | D30: Verdict
A31: ='Lead table'!$A$5 -> Chrysalis as drawn (~1% c) | B31: ='Lead table'!$Q$5 -> 0.022345639 | C31: ='Lead table'!$W$5 -> 4.2280033 | D31: =IF(C31>B31,"Safe door — "&'Lead table'!$R$5&" into the past","CLOSED TIMELIKE CURVE — "&'Lead table'!$R$5&" of lead with no light-time to hide it") -> Safe door — 8.2 days into the past
A32: ='Lead table'!$A$6 -> Fusion pushed to Daedalus speed (0.1 c) | B32: ='Lead table'!$Q$6 -> 0.21285848 | C32: ='Lead table'!$W$6 -> 4.2465 | D32: =IF(C32>B32,"Safe door — "&'Lead table'!$R$6&" into the past","CLOSED TIMELIKE CURVE — "&'Lead table'!$R$6&" of lead with no light-time to hide it") -> Safe door — 2.6 months into the past
A33: ='Lead table'!$A$7 -> 1 g torch to Proxima | B33: ='Lead table'!$Q$7 -> 2.3304996 | C33: ='Lead table'!$W$7 -> 4.2465 | D33: =IF(C33>B33,"Safe door — "&'Lead table'!$R$7&" into the past","CLOSED TIMELIKE CURVE — "&'Lead table'!$R$7&" of lead with no light-time to hide it") -> Safe door — 2.3 years into the past
A34: ='Lead table'!$A$8 -> 1 g, 1,000 ly and back | B34: ='Lead table'!$Q$8 -> 1976.9739 | C34: ='Lead table'!$W$8 -> 0 | D34: =IF(C34>B34,"Safe door — "&'Lead table'!$R$8&" into the past","CLOSED TIMELIKE CURVE — "&'Lead table'!$R$8&" of lead with no light-time to hide it") -> CLOSED TIMELIKE CURVE — 1,977 years of lead with no light-time to hide it
A35: ='Lead table'!$A$9 -> 1 g to the galactic centre | B35: ='Lead table'!$Q$9 -> 25982.18 | C35: ='Lead table'!$W$9 -> 26000 | D35: =IF(C35>B35,"Safe door — "&'Lead table'!$R$9&" into the past","CLOSED TIMELIKE CURVE — "&'Lead table'!$R$9&" of lead with no light-time to hide it") -> Safe door — 25,982 years into the past
A36: ='Lead table'!$A$10 -> Your ship A (torch) | B36: ='Lead table'!$Q$10 -> 88.374898 | C36: ='Lead table'!$W$10 -> 100 | D36: =IF(C36>B36,"Safe door — "&'Lead table'!$R$10&" into the past","CLOSED TIMELIKE CURVE — "&'Lead table'!$R$10&" of lead with no light-time to hide it") -> Safe door — 88 years into the past
A37: ='Lead table'!$A$11 -> Your ship B (coast) | B37: ='Lead table'!$Q$11 -> 1.1378462 | C37: ='Lead table'!$W$11 -> 4.2465 | D37: =IF(C37>B37,"Safe door — "&'Lead table'!$R$11&" into the past","CLOSED TIMELIKE CURVE — "&'Lead table'!$R$11&" of lead with no light-time to hide it") -> Safe door — 1.1 years into the past
A38: Chrysalis as drawn with a wormhole in the hold is a door eight days into the past; the 1 g Proxima version is a door 2.3 years deep. The 1,000-ly round trip brings the mouth home with a two-millennium lag and zero separation — the textbook wormhole time machine, and exactly where chronology protection says the vacuum blows up.
A39: What it does to a generation ship: it deletes the one thing that defines one — isolation — and replaces it with something stranger. You can go home whenever you like, but home is always a little in the past.

Sheet Nautilus
A1: Nautilus — time as cargo: the core is an archive
A2: No new physics. Chrysalis nests its shells in space; Nautilus nests them in time. Each generation builds the next chamber onto the axis and seals the one it grew up in exactly as it was lived, so the ship arrives longer than it left — a line of sealed eras you can walk back through.
A5: Inputs
A6: Quantity | B6: Value | C6: Unit | D6: Notes / source
A7: Wished-for chamber length per generation | B7: 1000 | C7: m | D7: Assumption
A8: Empty tankage mass per kg of fuel it held | B8: 0.05 | C8: kg/kg | D8: Cryogenic tanks run ~5–10% of the propellant mass; this is the 'slag' the chambers are built from
A9: Radius of the archive ring (sealed chambers sit inboard of the living rim) | B9: 2000 | C9: m | D9: Assumption
A10: Generation length | B10: =Chrysalis!$B$21 -> 27 | C10: years | D10: Chrysalis sheet
A11: Journey | B11: =Chrysalis!$B$13 -> 400 | C11: years | D11: Chrysalis sheet
A12: Ship length at launch | B12: =Chrysalis!$B$30 -> 58000 | C12: m | D12: Chrysalis sheet
A13: Ship dry mass | B13: =Chrysalis!$B$31 -> 2400000000000 | C13: kg | D13: Chrysalis sheet
A14: Rim radius | B14: =Chrysalis!$B$29 -> 3000 | C14: m | D14: Chrysalis sheet
A15: Rim speed | B15: =Chrysalis!$B$41 -> 171.52245 | C15: m/s | D15: Chrysalis sheet
A16: Rim gravity | B16: =Chrysalis!$B$14 -> 1 | C16: g | D16: Chrysalis sheet
A17: Fuel mass burned on the way | B17: =Chrysalis!$B$80 -> 2.1281075e+12 | C17: kg | D17: Chrysalis sheet
A18: Everything the nose sweeps up in the whole crossing (gas + dust) | B18: =Chrysalis!$B$93+Chrysalis!$B$94 -> 1910.6077 | C18: kg | D18: 'Whatever it mines en route' is this: a rounding error. The building stock has to be the ship's own spent tankage.
A20: Growing the ship
A21: Quantity | B21: Value | C21: Unit | D21: Notes / source
A22: Generations over the journey | B22: =$B$11/$B$10 -> 14.814815
A23: Sealed chambers at arrival | B23: =INT($B$22) -> 14
A24: Hull mass per metre of ship, as built | B24: =$B$13/$B$12 -> 41379310 | C24: kg/m
A25: Mass of one wished-for chamber | B25: =$B$24*$B$7 -> 4.137931e+10 | C25: kg
A26: …for all chambers | B26: =$B$25*$B$23 -> 5.7931034e+11 | C26: kg
A27: Length added by arrival | B27: =$B$7*$B$23 -> 14000 | C27: m
A28: Length at arrival | B28: =($B$12+$B$27)/1000 -> 72 | C28: km | D28: The ship arrives longer than it left
A29: Growth | B29: =$B$27/$B$12 -> 0.24137931
A30: Building stock: spent tankage | B30: =$B$17*$B$8 -> 1.0640537e+11 | C30: kg
A31: Share of the wished-for chambers the stock can build | B31: =$B$30/$B$26 -> 0.18367594 | D31: Below 100%, the chambers must be shorter or thinner-walled than the original hull
A32: Affordable chamber length per generation, built like the hull | B32: =$B$30/$B$24/$B$23 -> 183.67594 | C32: m
A33: …total archive length at arrival | B33: =$B$32*$B$23 -> 2571.4632 | C33: m
A35: Walking back through time
A36: Quantity | B36: Value | C36: Unit | D36: Notes / source
A37: Metres of ship per year of history (wished-for chambers) | B37: =$B$7/$B$10 -> 37.037037 | C37: m/yr
A38: …centimetres per day | B38: =$B$37*100/365.25 -> 10.140188 | C38: cm/day
A39: Walk from the newest chamber to year 0 | B39: =$B$27/1000 -> 14 | C39: km
A40: Same walk with the affordable chambers | B40: =$B$33/1000 -> 2.5714632 | C40: km
A42: Spin balance as it grows
A43: Quantity | B43: Value | C43: Unit | D43: Notes / source
A44: Energy to spin up one chamber to rim speed, ½mv² | B44: =0.5*$B$25*$B$15^2 -> 608688620689655 | C44: J
A45: …in GWh | B45: =$B$44/3600000000000 -> 169.08017 | C45: GWh | D45: About a day of a large power station per chamber
A46: Rim gravity if a chamber is bolted on without spinning it up | B46: =$B$16*($B$13/($B$13+$B$25))^2 -> 0.96638897 | C46: g | D46: Angular momentum conserved, thin-shell approximation: ω falls, and g at the rim falls with ω²
A47: Centre of mass | B47: Chambers must be added at the axis or in matched pairs, or the spin axis wanders
A49: Each era keeps its own clock
A50: Quantity | B50: Value | C50: Unit | D50: Notes / source
A51: Speed of the archive ring | B51: =$B$15*$B$9/$B$14 -> 114.3483 | C51: m/s
A52: Archive clock runs fast relative to the living rim by (v_rim² − v_arch²)/2c² | B52: =($B$15^2-$B$51^2)/(2*Constants!$B$7^2) -> 9.0928081e-14 | C52: fraction
A53: …nanoseconds per day | B53: =$B$52*Constants!$B$11*1000000000 -> 7.8561862 | C53: ns/day
A54: A chamber sealed in year 0 and opened on arrival has run ahead by | B54: =$B$52*$B$11*Constants!$B$10*1000 -> 1.1477888 | C54: ms | D54: Measurable with the project's own cesium clocks
A55: The engineering problem is a civil one — a structure that must stay balanced while it grows and spins — and the social one is deciding what a generation is allowed to leave out. It inverts the old trope of the crew who forget they are on a ship: the ship remembers so the people don't have to.

Sheet Vigil
A1: Vigil — pupation: the core is a vault
A2: The slowest time machine: sleep through it. Everyone Chrysalis can carry goes into cold storage (the one piece of technology here that nobody has) and the ship is tended by a small watch at a time. The watch roster is the ship's calendar.
A5: Inputs
A6: Quantity | B6: Value | C6: Unit | D6: Notes / source
A7: People aboard | B7: =Chrysalis!$B$10 -> 2400 | C7: people | D7: Chrysalis capacity
A8: Awake at any one time | B8: 60 | C8: people | D8: Assumption
A9: Watch length | B9: 10 | C9: years | D9: Assumption
A10: Journey | B10: =Chrysalis!$B$13 -> 400 | C10: years | D10: Chrysalis sheet
A11: Volume per storage pod | B11: 3 | C11: m³ | D11: Assumption
A12: Holding power per pod | B12: 150 | C12: W | D12: Assumption — cryostat losses plus monitoring
A13: Pressurised volume per awake person (quarters, farms, commons) | B13: 300 | C13: m³ | D13: Assumption
A14: Share of the ship's dry mass that scales with pressurised volume | B14: 0.5 | D14: Assumption
A15: Launch year | B15: =Chrysalis!$B$22 -> 2125 | C15: year | D15: Chrysalis sheet
A16: Boarding age | B16: =Chrysalis!$B$23 -> 25 | C16: years | D16: Chrysalis sheet
A17: Ship dry mass | B17: =Chrysalis!$B$31 -> 2400000000000 | C17: kg | D17: Chrysalis sheet
A18: Fuel mass | B18: =Chrysalis!$B$80 -> 2.1281075e+12 | C18: kg | D18: Chrysalis sheet
A19: Exhaust velocity | B19: =Chrysalis!$B$19 -> 0.0333 | C19: × c | D19: Chrysalis sheet
A20: Distance | B20: =Chrysalis!$B$32 -> 4e+16 | C20: m | D20: Chrysalis sheet
A21: Relativistic lead of Chrysalis as drawn | B21: ='Lead table'!$Q$5*365.25 -> 8.1617448 | C21: days | D21: Lead table, row 5
A23: The roster arithmetic
A24: Quantity | B24: Value | C24: Unit | D24: Notes / source
A25: Watches over the journey | B25: =$B$10/$B$9 -> 40
A26: Person-watches available | B26: =$B$25*$B$8 -> 2400
A27: Watches per person | B27: =$B$26/$B$7 -> 1 | D27: Exactly 1 with the defaults: everyone serves once — 'one decade awake, thirty-nine asleep'
A28: Years awake per person | B28: =$B$27*$B$9 -> 10 | C28: years
A29: Years asleep per person | B29: =$B$10-$B$28 -> 390 | C29: years | D29: This is the time machine: the sleep is the jump
A30: Fraction of the people awake | B30: =$B$8/$B$7 -> 0.025
A31: Biological age at arrival (if storage halts ageing) | B31: =$B$16+$B$28 -> 35 | C31: years
A32: Calendar age at arrival | B32: =$B$16+$B$10 -> 425 | C32: years
A33: Pods occupied at any time | B33: =$B$7-$B$8 -> 2340 | C33: pods
A34: Pod volume, total | B34: =$B$33*$B$11 -> 7020 | C34: m³
A35: Holding power, total | B35: =$B$33*$B$12/1000 -> 351 | C35: kW | D35: Trivial beside a fusion plant; the hard part is the biology, not the power
A37: Less mass awake means faster — same fuel, lighter ship
A38: Quantity | B38: Value | C38: Unit | D38: Notes / source
A39: Pressurised volume needed, Vigil | B39: =$B$8*$B$13+$B$33*$B$11 -> 25020 | C39: m³
A40: Pressurised volume needed, everyone awake | B40: =$B$7*$B$13 -> 720000 | C40: m³
A41: Ratio | B41: =$B$39/$B$40 -> 0.03475
A42: Dry mass of the Vigil ship | B42: =$B$17*(1-$B$14*(1-$B$41)) -> 1241700000000 | C42: kg
A43: Δv with the same fuel, vₑ·ln(M₀/M₁) | B43: =$B$19*Constants!$B$7*LN(($B$42+$B$18)/$B$42) -> 9966858.4 | C43: m/s
A44: Cruise speed (half the Δv goes to braking) | B44: =$B$43/2 -> 4983429.2 | C44: m/s
A45: …as a fraction of c | B45: =$B$44/Constants!$B$7 -> 0.01662293 | C45: × c
A46: Journey time | B46: =$B$20/$B$44/Constants!$B$10 -> 254.34765 | C46: years
A47: Years saved against Chrysalis as drawn | B47: =$B$10-$B$46 -> 145.65235 | C47: years | D47: Modest: fuel, not habitat, is what a fusion ship is mostly made of. The chrysalis stops being a metaphor; the speed-up is a bonus.
A49: The watch roster — the ship's calendar
A50: Watch | B50: Mission year (start → end) | C50: Earth calendar at wake | D50: Who is awake
A51: =IF(1<=$B$25,1,"") -> 1 | B51: =IF(1<=$B$25,TEXT((1-1)*$B$9,"0")&" → "&TEXT(1*$B$9,"0"),"") -> 0 → 10 | C51: =IF(1<=$B$25,$B$15+(1-1)*$B$9,"") -> 2125 | D51: =IF(1<=$B$25,"Sleepers "&TEXT((1-1)*$B$8+1,"#,##0")&"–"&TEXT(1*$B$8,"#,##0")&" — they wake "&TEXT((1-1)*$B$9,"0")&" years after launch, among strangers from a century they never saw","") -> Sleepers 1–60 — they wake 0 years after launch, among strangers from a century they never saw
A52: =IF(2<=$B$25,2,"") -> 2 | B52: =IF(2<=$B$25,TEXT((2-1)*$B$9,"0")&" → "&TEXT(2*$B$9,"0"),"") -> 10 → 20 | C52: =IF(2<=$B$25,$B$15+(2-1)*$B$9,"") -> 2135 | D52: =IF(2<=$B$25,"Sleepers "&TEXT((2-1)*$B$8+1,"#,##0")&"–"&TEXT(2*$B$8,"#,##0")&" — they wake "&TEXT((2-1)*$B$9,"0")&" years after launch, among strangers from a century they never saw","") -> Sleepers 61–120 — they wake 10 years after launch, among strangers from a century they never saw
A53: =IF(3<=$B$25,3,"") -> 3 | B53: =IF(3<=$B$25,TEXT((3-1)*$B$9,"0")&" → "&TEXT(3*$B$9,"0"),"") -> 20 → 30 | C53: =IF(3<=$B$25,$B$15+(3-1)*$B$9,"") -> 2145 | D53: =IF(3<=$B$25,"Sleepers "&TEXT((3-1)*$B$8+1,"#,##0")&"–"&TEXT(3*$B$8,"#,##0")&" — they wake "&TEXT((3-1)*$B$9,"0")&" years after launch, among strangers from a century they never saw","") -> Sleepers 121–180 — they wake 20 years after launch, among strangers from a century they never saw
A54: =IF(4<=$B$25,4,"") -> 4 | B54: =IF(4<=$B$25,TEXT((4-1)*$B$9,"0")&" → "&TEXT(4*$B$9,"0"),"") -> 30 → 40 | C54: =IF(4<=$B$25,$B$15+(4-1)*$B$9,"") -> 2155 | D54: =IF(4<=$B$25,"Sleepers "&TEXT((4-1)*$B$8+1,"#,##0")&"–"&TEXT(4*$B$8,"#,##0")&" — they wake "&TEXT((4-1)*$B$9,"0")&" years after launch, among strangers from a century they never saw","") -> Sleepers 181–240 — they wake 30 years after launch, among strangers from a century they never saw
A55: =IF(5<=$B$25,5,"") -> 5 | B55: =IF(5<=$B$25,TEXT((5-1)*$B$9,"0")&" → "&TEXT(5*$B$9,"0"),"") -> 40 → 50 | C55: =IF(5<=$B$25,$B$15+(5-1)*$B$9,"") -> 2165 | D55: =IF(5<=$B$25,"Sleepers "&TEXT((5-1)*$B$8+1,"#,##0")&"–"&TEXT(5*$B$8,"#,##0")&" — they wake "&TEXT((5-1)*$B$9,"0")&" years after launch, among strangers from a century they never saw","") -> Sleepers 241–300 — they wake 40 years after launch, among strangers from a century they never saw
A56: =IF(6<=$B$25,6,"") -> 6 | B56: =IF(6<=$B$25,TEXT((6-1)*$B$9,"0")&" → "&TEXT(6*$B$9,"0"),"") -> 50 → 60 | C56: =IF(6<=$B$25,$B$15+(6-1)*$B$9,"") -> 2175 | D56: =IF(6<=$B$25,"Sleepers "&TEXT((6-1)*$B$8+1,"#,##0")&"–"&TEXT(6*$B$8,"#,##0")&" — they wake "&TEXT((6-1)*$B$9,"0")&" years after launch, among strangers from a century they never saw","") -> Sleepers 301–360 — they wake 50 years after launch, among strangers from a century they never saw
A57: =IF(7<=$B$25,7,"") -> 7 | B57: =IF(7<=$B$25,TEXT((7-1)*$B$9,"0")&" → "&TEXT(7*$B$9,"0"),"") -> 60 → 70 | C57: =IF(7<=$B$25,$B$15+(7-1)*$B$9,"") -> 2185 | D57: =IF(7<=$B$25,"Sleepers "&TEXT((7-1)*$B$8+1,"#,##0")&"–"&TEXT(7*$B$8,"#,##0")&" — they wake "&TEXT((7-1)*$B$9,"0")&" years after launch, among strangers from a century they never saw","") -> Sleepers 361–420 — they wake 60 years after launch, among strangers from a century they never saw
A58: =IF(8<=$B$25,8,"") -> 8 | B58: =IF(8<=$B$25,TEXT((8-1)*$B$9,"0")&" → "&TEXT(8*$B$9,"0"),"") -> 70 → 80 | C58: =IF(8<=$B$25,$B$15+(8-1)*$B$9,"") -> 2195 | D58: =IF(8<=$B$25,"Sleepers "&TEXT((8-1)*$B$8+1,"#,##0")&"–"&TEXT(8*$B$8,"#,##0")&" — they wake "&TEXT((8-1)*$B$9,"0")&" years after launch, among strangers from a century they never saw","") -> Sleepers 421–480 — they wake 70 years after launch, among strangers from a century they never saw
A59: =IF(9<=$B$25,9,"") -> 9 | B59: =IF(9<=$B$25,TEXT((9-1)*$B$9,"0")&" → "&TEXT(9*$B$9,"0"),"") -> 80 → 90 | C59: =IF(9<=$B$25,$B$15+(9-1)*$B$9,"") -> 2205 | D59: =IF(9<=$B$25,"Sleepers "&TEXT((9-1)*$B$8+1,"#,##0")&"–"&TEXT(9*$B$8,"#,##0")&" — they wake "&TEXT((9-1)*$B$9,"0")&" years after launch, among strangers from a century they never saw","") -> Sleepers 481–540 — they wake 80 years after launch, among strangers from a century they never saw
A60: =IF(10<=$B$25,10,"") -> 10 | B60: =IF(10<=$B$25,TEXT((10-1)*$B$9,"0")&" → "&TEXT(10*$B$9,"0"),"") -> 90 → 100 | C60: =IF(10<=$B$25,$B$15+(10-1)*$B$9,"") -> 2215 | D60: =IF(10<=$B$25,"Sleepers "&TEXT((10-1)*$B$8+1,"#,##0")&"–"&TEXT(10*$B$8,"#,##0")&" — they wake "&TEXT((10-1)*$B$9,"0")&" years after launch, among strangers from a century they never saw","") -> Sleepers 541–600 — they wake 90 years after launch, among strangers from a century they never saw
A61: =IF(11<=$B$25,11,"") -> 11 | B61: =IF(11<=$B$25,TEXT((11-1)*$B$9,"0")&" → "&TEXT(11*$B$9,"0"),"") -> 100 → 110 | C61: =IF(11<=$B$25,$B$15+(11-1)*$B$9,"") -> 2225 | D61: =IF(11<=$B$25,"Sleepers "&TEXT((11-1)*$B$8+1,"#,##0")&"–"&TEXT(11*$B$8,"#,##0")&" — they wake "&TEXT((11-1)*$B$9,"0")&" years after launch, among strangers from a century they never saw","") -> Sleepers 601–660 — they wake 100 years after launch, among strangers from a century they never saw
A62: =IF(12<=$B$25,12,"") -> 12 | B62: =IF(12<=$B$25,TEXT((12-1)*$B$9,"0")&" → "&TEXT(12*$B$9,"0"),"") -> 110 → 120 | C62: =IF(12<=$B$25,$B$15+(12-1)*$B$9,"") -> 2235 | D62: =IF(12<=$B$25,"Sleepers "&TEXT((12-1)*$B$8+1,"#,##0")&"–"&TEXT(12*$B$8,"#,##0")&" — they wake "&TEXT((12-1)*$B$9,"0")&" years after launch, among strangers from a century they never saw","") -> Sleepers 661–720 — they wake 110 years after launch, among strangers from a century they never saw
A63: =IF(13<=$B$25,13,"") -> 13 | B63: =IF(13<=$B$25,TEXT((13-1)*$B$9,"0")&" → "&TEXT(13*$B$9,"0"),"") -> 120 → 130 | C63: =IF(13<=$B$25,$B$15+(13-1)*$B$9,"") -> 2245 | D63: =IF(13<=$B$25,"Sleepers "&TEXT((13-1)*$B$8+1,"#,##0")&"–"&TEXT(13*$B$8,"#,##0")&" — they wake "&TEXT((13-1)*$B$9,"0")&" years after launch, among strangers from a century they never saw","") -> Sleepers 721–780 — they wake 120 years after launch, among strangers from a century they never saw
A64: =IF(14<=$B$25,14,"") -> 14 | B64: =IF(14<=$B$25,TEXT((14-1)*$B$9,"0")&" → "&TEXT(14*$B$9,"0"),"") -> 130 → 140 | C64: =IF(14<=$B$25,$B$15+(14-1)*$B$9,"") -> 2255 | D64: =IF(14<=$B$25,"Sleepers "&TEXT((14-1)*$B$8+1,"#,##0")&"–"&TEXT(14*$B$8,"#,##0")&" — they wake "&TEXT((14-1)*$B$9,"0")&" years after launch, among strangers from a century they never saw","") -> Sleepers 781–840 — they wake 130 years after launch, among strangers from a century they never saw
A65: =IF(15<=$B$25,15,"") -> 15 | B65: =IF(15<=$B$25,TEXT((15-1)*$B$9,"0")&" → "&TEXT(15*$B$9,"0"),"") -> 140 → 150 | C65: =IF(15<=$B$25,$B$15+(15-1)*$B$9,"") -> 2265 | D65: =IF(15<=$B$25,"Sleepers "&TEXT((15-1)*$B$8+1,"#,##0")&"–"&TEXT(15*$B$8,"#,##0")&" — they wake "&TEXT((15-1)*$B$9,"0")&" years after launch, among strangers from a century they never saw","") -> Sleepers 841–900 — they wake 140 years after launch, among strangers from a century they never saw
A66: =IF(16<=$B$25,16,"") -> 16 | B66: =IF(16<=$B$25,TEXT((16-1)*$B$9,"0")&" → "&TEXT(16*$B$9,"0"),"") -> 150 → 160 | C66: =IF(16<=$B$25,$B$15+(16-1)*$B$9,"") -> 2275 | D66: =IF(16<=$B$25,"Sleepers "&TEXT((16-1)*$B$8+1,"#,##0")&"–"&TEXT(16*$B$8,"#,##0")&" — they wake "&TEXT((16-1)*$B$9,"0")&" years after launch, among strangers from a century they never saw","") -> Sleepers 901–960 — they wake 150 years after launch, among strangers from a century they never saw
A67: =IF(17<=$B$25,17,"") -> 17 | B67: =IF(17<=$B$25,TEXT((17-1)*$B$9,"0")&" → "&TEXT(17*$B$9,"0"),"") -> 160 → 170 | C67: =IF(17<=$B$25,$B$15+(17-1)*$B$9,"") -> 2285 | D67: =IF(17<=$B$25,"Sleepers "&TEXT((17-1)*$B$8+1,"#,##0")&"–"&TEXT(17*$B$8,"#,##0")&" — they wake "&TEXT((17-1)*$B$9,"0")&" years after launch, among strangers from a century they never saw","") -> Sleepers 961–1,020 — they wake 160 years after launch, among strangers from a century they never saw
A68: =IF(18<=$B$25,18,"") -> 18 | B68: =IF(18<=$B$25,TEXT((18-1)*$B$9,"0")&" → "&TEXT(18*$B$9,"0"),"") -> 170 → 180 | C68: =IF(18<=$B$25,$B$15+(18-1)*$B$9,"") -> 2295 | D68: =IF(18<=$B$25,"Sleepers "&TEXT((18-1)*$B$8+1,"#,##0")&"–"&TEXT(18*$B$8,"#,##0")&" — they wake "&TEXT((18-1)*$B$9,"0")&" years after launch, among strangers from a century they never saw","") -> Sleepers 1,021–1,080 — they wake 170 years after launch, among strangers from a century they never saw
A69: =IF(19<=$B$25,19,"") -> 19 | B69: =IF(19<=$B$25,TEXT((19-1)*$B$9,"0")&" → "&TEXT(19*$B$9,"0"),"") -> 180 → 190 | C69: =IF(19<=$B$25,$B$15+(19-1)*$B$9,"") -> 2305 | D69: =IF(19<=$B$25,"Sleepers "&TEXT((19-1)*$B$8+1,"#,##0")&"–"&TEXT(19*$B$8,"#,##0")&" — they wake "&TEXT((19-1)*$B$9,"0")&" years after launch, among strangers from a century they never saw","") -> Sleepers 1,081–1,140 — they wake 180 years after launch, among strangers from a century they never saw
A70: =IF(20<=$B$25,20,"") -> 20 | B70: =IF(20<=$B$25,TEXT((20-1)*$B$9,"0")&" → "&TEXT(20*$B$9,"0"),"") -> 190 → 200 | C70: =IF(20<=$B$25,$B$15+(20-1)*$B$9,"") -> 2315 | D70: =IF(20<=$B$25,"Sleepers "&TEXT((20-1)*$B$8+1,"#,##0")&"–"&TEXT(20*$B$8,"#,##0")&" — they wake "&TEXT((20-1)*$B$9,"0")&" years after launch, among strangers from a century they never saw","") -> Sleepers 1,141–1,200 — they wake 190 years after launch, among strangers from a century they never saw
A71: =IF(21<=$B$25,21,"") -> 21 | B71: =IF(21<=$B$25,TEXT((21-1)*$B$9,"0")&" → "&TEXT(21*$B$9,"0"),"") -> 200 → 210 | C71: =IF(21<=$B$25,$B$15+(21-1)*$B$9,"") -> 2325 | D71: =IF(21<=$B$25,"Sleepers "&TEXT((21-1)*$B$8+1,"#,##0")&"–"&TEXT(21*$B$8,"#,##0")&" — they wake "&TEXT((21-1)*$B$9,"0")&" years after launch, among strangers from a century they never saw","") -> Sleepers 1,201–1,260 — they wake 200 years after launch, among strangers from a century they never saw
A72: =IF(22<=$B$25,22,"") -> 22 | B72: =IF(22<=$B$25,TEXT((22-1)*$B$9,"0")&" → "&TEXT(22*$B$9,"0"),"") -> 210 → 220 | C72: =IF(22<=$B$25,$B$15+(22-1)*$B$9,"") -> 2335 | D72: =IF(22<=$B$25,"Sleepers "&TEXT((22-1)*$B$8+1,"#,##0")&"–"&TEXT(22*$B$8,"#,##0")&" — they wake "&TEXT((22-1)*$B$9,"0")&" years after launch, among strangers from a century they never saw","") -> Sleepers 1,261–1,320 — they wake 210 years after launch, among strangers from a century they never saw
A73: =IF(23<=$B$25,23,"") -> 23 | B73: =IF(23<=$B$25,TEXT((23-1)*$B$9,"0")&" → "&TEXT(23*$B$9,"0"),"") -> 220 → 230 | C73: =IF(23<=$B$25,$B$15+(23-1)*$B$9,"") -> 2345 | D73: =IF(23<=$B$25,"Sleepers "&TEXT((23-1)*$B$8+1,"#,##0")&"–"&TEXT(23*$B$8,"#,##0")&" — they wake "&TEXT((23-1)*$B$9,"0")&" years after launch, among strangers from a century they never saw","") -> Sleepers 1,321–1,380 — they wake 220 years after launch, among strangers from a century they never saw
A74: =IF(24<=$B$25,24,"") -> 24 | B74: =IF(24<=$B$25,TEXT((24-1)*$B$9,"0")&" → "&TEXT(24*$B$9,"0"),"") -> 230 → 240 | C74: =IF(24<=$B$25,$B$15+(24-1)*$B$9,"") -> 2355 | D74: =IF(24<=$B$25,"Sleepers "&TEXT((24-1)*$B$8+1,"#,##0")&"–"&TEXT(24*$B$8,"#,##0")&" — they wake "&TEXT((24-1)*$B$9,"0")&" years after launch, among strangers from a century they never saw","") -> Sleepers 1,381–1,440 — they wake 230 years after launch, among strangers from a century they never saw
A75: =IF(25<=$B$25,25,"") -> 25 | B75: =IF(25<=$B$25,TEXT((25-1)*$B$9,"0")&" → "&TEXT(25*$B$9,"0"),"") -> 240 → 250 | C75: =IF(25<=$B$25,$B$15+(25-1)*$B$9,"") -> 2365 | D75: =IF(25<=$B$25,"Sleepers "&TEXT((25-1)*$B$8+1,"#,##0")&"–"&TEXT(25*$B$8,"#,##0")&" — they wake "&TEXT((25-1)*$B$9,"0")&" years after launch, among strangers from a century they never saw","") -> Sleepers 1,441–1,500 — they wake 240 years after launch, among strangers from a century they never saw
A76: =IF(26<=$B$25,26,"") -> 26 | B76: =IF(26<=$B$25,TEXT((26-1)*$B$9,"0")&" → "&TEXT(26*$B$9,"0"),"") -> 250 → 260 | C76: =IF(26<=$B$25,$B$15+(26-1)*$B$9,"") -> 2375 | D76: =IF(26<=$B$25,"Sleepers "&TEXT((26-1)*$B$8+1,"#,##0")&"–"&TEXT(26*$B$8,"#,##0")&" — they wake "&TEXT((26-1)*$B$9,"0")&" years after launch, among strangers from a century they never saw","") -> Sleepers 1,501–1,560 — they wake 250 years after launch, among strangers from a century they never saw
A77: =IF(27<=$B$25,27,"") -> 27 | B77: =IF(27<=$B$25,TEXT((27-1)*$B$9,"0")&" → "&TEXT(27*$B$9,"0"),"") -> 260 → 270 | C77: =IF(27<=$B$25,$B$15+(27-1)*$B$9,"") -> 2385 | D77: =IF(27<=$B$25,"Sleepers "&TEXT((27-1)*$B$8+1,"#,##0")&"–"&TEXT(27*$B$8,"#,##0")&" — they wake "&TEXT((27-1)*$B$9,"0")&" years after launch, among strangers from a century they never saw","") -> Sleepers 1,561–1,620 — they wake 260 years after launch, among strangers from a century they never saw
A78: =IF(28<=$B$25,28,"") -> 28 | B78: =IF(28<=$B$25,TEXT((28-1)*$B$9,"0")&" → "&TEXT(28*$B$9,"0"),"") -> 270 → 280 | C78: =IF(28<=$B$25,$B$15+(28-1)*$B$9,"") -> 2395 | D78: =IF(28<=$B$25,"Sleepers "&TEXT((28-1)*$B$8+1,"#,##0")&"–"&TEXT(28*$B$8,"#,##0")&" — they wake "&TEXT((28-1)*$B$9,"0")&" years after launch, among strangers from a century they never saw","") -> Sleepers 1,621–1,680 — they wake 270 years after launch, among strangers from a century they never saw
A79: =IF(29<=$B$25,29,"") -> 29 | B79: =IF(29<=$B$25,TEXT((29-1)*$B$9,"0")&" → "&TEXT(29*$B$9,"0"),"") -> 280 → 290 | C79: =IF(29<=$B$25,$B$15+(29-1)*$B$9,"") -> 2405 | D79: =IF(29<=$B$25,"Sleepers "&TEXT((29-1)*$B$8+1,"#,##0")&"–"&TEXT(29*$B$8,"#,##0")&" — they wake "&TEXT((29-1)*$B$9,"0")&" years after launch, among strangers from a century they never saw","") -> Sleepers 1,681–1,740 — they wake 280 years after launch, among strangers from a century they never saw
A80: =IF(30<=$B$25,30,"") -> 30 | B80: =IF(30<=$B$25,TEXT((30-1)*$B$9,"0")&" → "&TEXT(30*$B$9,"0"),"") -> 290 → 300 | C80: =IF(30<=$B$25,$B$15+(30-1)*$B$9,"") -> 2415 | D80: =IF(30<=$B$25,"Sleepers "&TEXT((30-1)*$B$8+1,"#,##0")&"–"&TEXT(30*$B$8,"#,##0")&" — they wake "&TEXT((30-1)*$B$9,"0")&" years after launch, among strangers from a century they never saw","") -> Sleepers 1,741–1,800 — they wake 290 years after launch, among strangers from a century they never saw
A81: =IF(31<=$B$25,31,"") -> 31 | B81: =IF(31<=$B$25,TEXT((31-1)*$B$9,"0")&" → "&TEXT(31*$B$9,"0"),"") -> 300 → 310 | C81: =IF(31<=$B$25,$B$15+(31-1)*$B$9,"") -> 2425 | D81: =IF(31<=$B$25,"Sleepers "&TEXT((31-1)*$B$8+1,"#,##0")&"–"&TEXT(31*$B$8,"#,##0")&" — they wake "&TEXT((31-1)*$B$9,"0")&" years after launch, among strangers from a century they never saw","") -> Sleepers 1,801–1,860 — they wake 300 years after launch, among strangers from a century they never saw
A82: =IF(32<=$B$25,32,"") -> 32 | B82: =IF(32<=$B$25,TEXT((32-1)*$B$9,"0")&" → "&TEXT(32*$B$9,"0"),"") -> 310 → 320 | C82: =IF(32<=$B$25,$B$15+(32-1)*$B$9,"") -> 2435 | D82: =IF(32<=$B$25,"Sleepers "&TEXT((32-1)*$B$8+1,"#,##0")&"–"&TEXT(32*$B$8,"#,##0")&" — they wake "&TEXT((32-1)*$B$9,"0")&" years after launch, among strangers from a century they never saw","") -> Sleepers 1,861–1,920 — they wake 310 years after launch, among strangers from a century they never saw
A83: =IF(33<=$B$25,33,"") -> 33 | B83: =IF(33<=$B$25,TEXT((33-1)*$B$9,"0")&" → "&TEXT(33*$B$9,"0"),"") -> 320 → 330 | C83: =IF(33<=$B$25,$B$15+(33-1)*$B$9,"") -> 2445 | D83: =IF(33<=$B$25,"Sleepers "&TEXT((33-1)*$B$8+1,"#,##0")&"–"&TEXT(33*$B$8,"#,##0")&" — they wake "&TEXT((33-1)*$B$9,"0")&" years after launch, among strangers from a century they never saw","") -> Sleepers 1,921–1,980 — they wake 320 years after launch, among strangers from a century they never saw
A84: =IF(34<=$B$25,34,"") -> 34 | B84: =IF(34<=$B$25,TEXT((34-1)*$B$9,"0")&" → "&TEXT(34*$B$9,"0"),"") -> 330 → 340 | C84: =IF(34<=$B$25,$B$15+(34-1)*$B$9,"") -> 2455 | D84: =IF(34<=$B$25,"Sleepers "&TEXT((34-1)*$B$8+1,"#,##0")&"–"&TEXT(34*$B$8,"#,##0")&" — they wake "&TEXT((34-1)*$B$9,"0")&" years after launch, among strangers from a century they never saw","") -> Sleepers 1,981–2,040 — they wake 330 years after launch, among strangers from a century they never saw
A85: =IF(35<=$B$25,35,"") -> 35 | B85: =IF(35<=$B$25,TEXT((35-1)*$B$9,"0")&" → "&TEXT(35*$B$9,"0"),"") -> 340 → 350 | C85: =IF(35<=$B$25,$B$15+(35-1)*$B$9,"") -> 2465 | D85: =IF(35<=$B$25,"Sleepers "&TEXT((35-1)*$B$8+1,"#,##0")&"–"&TEXT(35*$B$8,"#,##0")&" — they wake "&TEXT((35-1)*$B$9,"0")&" years after launch, among strangers from a century they never saw","") -> Sleepers 2,041–2,100 — they wake 340 years after launch, among strangers from a century they never saw
A86: =IF(36<=$B$25,36,"") -> 36 | B86: =IF(36<=$B$25,TEXT((36-1)*$B$9,"0")&" → "&TEXT(36*$B$9,"0"),"") -> 350 → 360 | C86: =IF(36<=$B$25,$B$15+(36-1)*$B$9,"") -> 2475 | D86: =IF(36<=$B$25,"Sleepers "&TEXT((36-1)*$B$8+1,"#,##0")&"–"&TEXT(36*$B$8,"#,##0")&" — they wake "&TEXT((36-1)*$B$9,"0")&" years after launch, among strangers from a century they never saw","") -> Sleepers 2,101–2,160 — they wake 350 years after launch, among strangers from a century they never saw
A87: =IF(37<=$B$25,37,"") -> 37 | B87: =IF(37<=$B$25,TEXT((37-1)*$B$9,"0")&" → "&TEXT(37*$B$9,"0"),"") -> 360 → 370 | C87: =IF(37<=$B$25,$B$15+(37-1)*$B$9,"") -> 2485 | D87: =IF(37<=$B$25,"Sleepers "&TEXT((37-1)*$B$8+1,"#,##0")&"–"&TEXT(37*$B$8,"#,##0")&" — they wake "&TEXT((37-1)*$B$9,"0")&" years after launch, among strangers from a century they never saw","") -> Sleepers 2,161–2,220 — they wake 360 years after launch, among strangers from a century they never saw
A88: =IF(38<=$B$25,38,"") -> 38 | B88: =IF(38<=$B$25,TEXT((38-1)*$B$9,"0")&" → "&TEXT(38*$B$9,"0"),"") -> 370 → 380 | C88: =IF(38<=$B$25,$B$15+(38-1)*$B$9,"") -> 2495 | D88: =IF(38<=$B$25,"Sleepers "&TEXT((38-1)*$B$8+1,"#,##0")&"–"&TEXT(38*$B$8,"#,##0")&" — they wake "&TEXT((38-1)*$B$9,"0")&" years after launch, among strangers from a century they never saw","") -> Sleepers 2,221–2,280 — they wake 370 years after launch, among strangers from a century they never saw
A89: =IF(39<=$B$25,39,"") -> 39 | B89: =IF(39<=$B$25,TEXT((39-1)*$B$9,"0")&" → "&TEXT(39*$B$9,"0"),"") -> 380 → 390 | C89: =IF(39<=$B$25,$B$15+(39-1)*$B$9,"") -> 2505 | D89: =IF(39<=$B$25,"Sleepers "&TEXT((39-1)*$B$8+1,"#,##0")&"–"&TEXT(39*$B$8,"#,##0")&" — they wake "&TEXT((39-1)*$B$9,"0")&" years after launch, among strangers from a century they never saw","") -> Sleepers 2,281–2,340 — they wake 380 years after launch, among strangers from a century they never saw
A90: =IF(40<=$B$25,40,"") -> 40 | B90: =IF(40<=$B$25,TEXT((40-1)*$B$9,"0")&" → "&TEXT(40*$B$9,"0"),"") -> 390 → 400 | C90: =IF(40<=$B$25,$B$15+(40-1)*$B$9,"") -> 2515 | D90: =IF(40<=$B$25,"Sleepers "&TEXT((40-1)*$B$8+1,"#,##0")&"–"&TEXT(40*$B$8,"#,##0")&" — they wake "&TEXT((40-1)*$B$9,"0")&" years after launch, among strangers from a century they never saw","") -> Sleepers 2,341–2,400 — they wake 390 years after launch, among strangers from a century they never saw
A91: Rows beyond the computed number of watches go blank; the table holds up to 40 watches. The human problem is Rip Van Winkle run in reverse: each watch is a different century's people, and the sleepers wake as strangers to those who kept them.

Sheet Constants
A1: Constants and shared assumptions
A2: Physical constants (fixed) and the handful of shared assumptions every other sheet reads. Blue = input you can edit; yellow = an assumption worth questioning; black = formula.
A5: Physical constants
A6: Quantity | B6: Value | C6: Unit | D6: Notes / source
A7: Speed of light c | B7: 299792458 | C7: m/s | D7: SI exact value
A8: Standard gravity g₀ | B8: 9.80665 | C8: m/s² | D8: CGPM 1901 definition
A9: Gravitational constant G | B9: 6.6743e-11 | C9: m³ kg⁻¹ s⁻² | D9: CODATA 2018
A10: Julian year | B10: =365.25*86400 -> 31557600 | C10: s | D10: IAU: 365.25 days of 86,400 s
A11: Day | B11: 86400 | C11: s
A12: Light-year | B12: =$B$7*$B$10 -> 9.4607305e+15 | C12: m | D12: c × Julian year (IAU definition)
A13: Astronomical unit | B13: 149597870700 | C13: m | D13: IAU 2012 definition
A14: GM of the Sun | B14: 1.3271244e+20 | C14: m³/s² | D14: IAU 2015 nominal solar mass parameter
A15: GM of the Earth | B15: 398600441800000 | C15: m³/s² | D15: IAU 2015 nominal
A16: Earth equatorial radius | B16: 6378100 | C16: m | D16: IAU 2015 nominal
A17: Earth mass | B17: 5.9722e+24 | C17: kg | D17: NASA planetary fact sheet
A18: Jupiter mass | B18: 1.8982e+27 | C18: kg | D18: NASA planetary fact sheet
A19: Solar luminosity | B19: 3.828e+26 | C19: W | D19: IAU 2015 nominal
A20: Proton mass | B20: 1.6726219e-27 | C20: kg | D20: CODATA 2018
A21: Electron-volt | B21: 1.6021766e-19 | C21: J | D21: SI exact value
A22: Proton rest energy m_p c² | B22: =$B$20*$B$7^2 -> 1.5032776e-10 | C22: J
A23: …in MeV | B23: =$B$22/$B$21/1000000 -> 938.27209 | C23: MeV | D23: Should read 938.27
A24: Stefan–Boltzmann constant σ | B24: 5.6703744e-08 | C24: W m⁻² K⁻⁴ | D24: CODATA 2018
A25: TNT equivalent | B25: 4184000 | C25: J/kg | D25: Convention: 1 kg TNT = 4.184 MJ
A27: Shared assumptions (edit these)
A28: Quantity | B28: Value | C28: Unit | D28: Notes / source
A29: Interstellar hydrogen density n | B29: 1 | C29: atoms/cm³ | D29: Conservative. The Local Interstellar Cloud the Sun sits in is ~0.2 cm⁻³; set 0.2 for the optimistic case. Used by the Chrysalis, Tower and Nautilus sheets.
A30: Dust-to-gas mass ratio in the ISM | B30: 0.01 | D30: Standard interstellar value (~1%)
A31: Road-bike tyre pressure (for scale) | B31: 0.7 | C31: MPa | D31: ≈100 psi
A33: The project's own clocks, for scale
A34: Quantity | B34: Value | C34: Unit | D34: Notes / source
A35: Mount Greylock summit height | B35: 1063 | C35: m (NAVD88) | D35: The Greylock Time Machine design (claude/greylock-time-machine.md)
A36: Cambridge home-station height | B36: 6 | C36: m | D36: Same design note
A37: Harvard Jefferson tower (Pound–Rebka 1959) | B37: 22.5 | C37: m | D37: First laboratory measurement of gravitational time dilation
A38: Greylock rate difference g₀Δh/c² | B38: =$B$8*($B$35-$B$36)/$B$7^2 -> 1.1533318e-13 | C38: fraction | D38: Should read 1.153E-13 — the design note's figure
A39: …as nanoseconds per day (one 'Greylock') | B39: =$B$38*$B$11*1000000000 -> 9.9647865 | C39: ns/day | D39: Should read 9.96 ns/day
A40: Jefferson-tower rate difference g₀h/c² | B40: =$B$8*$B$37/$B$7^2 -> 2.4550582e-15 | C40: fraction
A41: …as nanoseconds per day (one 'Jefferson') | B41: =$B$40*$B$11*1000000000 -> 0.21211703 | C41: ns/day | D41: Should read 0.21 ns/day
A43: Materials for the hoop-stress check
A44: Material | B44: Density (kg/m³) | C44: Strength (MPa) | D44: Note
A45: Structural steel (A36) | B45: 7850 | C45: 250 | D45: Yield strength
A46: Aluminium 6061-T6 | B46: 2700 | C46: 276 | D46: Yield strength
A47: Carbon-fibre laminate (unidirectional, fibre direction) | B47: 1600 | C47: 1500 | D47: Tensile, fibre direction only — a hoop wound from it
A48: Graphene (ideal single sheet) | B48: 2267 | C48: 130000 | D48: Intrinsic strength (Lee et al., Science 2008) — a ceiling, not a stock material
A50: Added for the second wing (9 Oct 2026)
A51: Quantity | B51: Value | C51: Unit | D51: Notes / source
A52: Planck constant h | B52: 6.6260701e-34 | C52: J·s | D52: SI exact value
A53: Solar radius R☉ | B53: 695700000 | C53: m | D53: IAU 2015 nominal
A54: Blackbody temperature at 1 AU (zero albedo) | B54: 279 | C54: K | D54: T(r) = 279 K / √(r/AU): isothermal-sphere blackbody equilibrium, zero albedo (L☉/(16πσd²))^¼; a flat sun-facing plate runs 2^¼–4^¼ hotter

Sheet Pendulum
A1: Pendulum — the ferry: the core is a return engine
A2: The ship that never arrives. It swings out at 1 g, turns, and comes home; whoever rides a swing steps off into Earth's future by the lead of that cycle. Chrysalis's shells become the terminal building and the core is an engine that always points home. Known physics end to end — the fare is the fuel.
A4: Inputs
A5: Quantity | B5: Value | C5: Unit | D5: Notes / source
A6: Proper acceleration | B6: 1 | C6: g | D6: Thrust gravity for the riders; 1 g keeps the terminal floors honest
A7: Years aboard per round trip (proper) | B7: 10 | C7: years | D7: Four equal phases: out-accel, out-brake, home-accel, home-brake — τ/4 each
A8: Cycles before refit | B8: 5 | C8: cycles | D8: Assumption
A9: Exhaust speed βₑ | B9: 1 | C9: × c | D9: βₑ = 1 is the perfect photon rocket — the floor on the fare, not an engine anyone has (Lead table note)
A10: Dry mass per rider | B10: =Chrysalis!$B$9/Chrysalis!$B$10 -> 1000000 | C10: t | D10: Chrysalis: 2.4 Gt / 2,400 people — a million tonnes of ship per rider
A12: One swing of the pendulum
A13: Quantity | B13: Value | C13: Unit | D13: Notes / source
A14: c/a | B14: =Constants!$B$7/($B$6*Constants!$B$8)/Constants!$B$10 -> 0.96871508 | C14: years
A15: Rapidity per phase, φ = (τ/4)/(c/a) | B15: =($B$7/4)/$B$14 -> 2.5807382
A16: Peak speed, tanh φ | B16: =TANH($B$15) -> 0.98859891 | C16: × c
A17: Furthest reach, 2(c/a)(cosh φ − 1) | B17: =2*$B$14*(COSH($B$15)-1) -> 10.929627 | C17: ly | D17: c²/a in light-years equals c/a in years
A18: Earth time per cycle, 4(c/a)·sinh φ | B18: =4*$B$14*SINH($B$15) -> 25.440716 | C18: years
A19: Lead per cycle | B19: =$B$18-$B$7 -> 15.440716 | C19: years
A20: …readable | B20: =IF($B$19<1/12,TEXT($B$19*365.25,"0.0")&" days",IF($B$19<1,TEXT($B$19*12,"0.0")&" months",TEXT($B$19,"0.0")&" years")) -> 15.4 years | D20: What one ticket buys
A21: Mass ratio per cycle, exp(4φ/βₑ) | B21: =EXP(4*$B$15/$B$9) -> 30422.957 | C21: × | D21: Four boosts of φ each; the relativistic rocket equation at its least merciful
A22: Fuel per tonne of ship per cycle | B22: =$B$21-1 -> 30421.957 | C22: t
A23: Fuel per rider per cycle | B23: =$B$22*$B$10 -> 3.0421957e+10 | C23: t | D23: The fare in perfect-photon propellant
A24: Fuel per rider per year of lead | B24: =$B$23/$B$19 -> 1.9702426e+09 | C24: t/yr | D24: The ferry's price list: tonnes of fuel per year of future delivered
A26: The timetable
A27: Cycle | B27: Ship clock at return (yr aboard) | C27: Earth calendar at return | D27: Cumulative lead
A28: =IF(1<=$B$8,1,"") -> 1 | B28: =IF(1<=$B$8,1*$B$7,"") -> 10 | C28: =IF(1<=$B$8,TEXT(Chrysalis!$B$22+1*$B$18,"0"),"") -> 2150 | D28: =IF(1<=$B$8,TEXT(1*($B$18-$B$7),"0.0")&" years ahead of staying home","") -> 15.4 years ahead of staying home
A29: =IF(2<=$B$8,2,"") -> 2 | B29: =IF(2<=$B$8,2*$B$7,"") -> 20 | C29: =IF(2<=$B$8,TEXT(Chrysalis!$B$22+2*$B$18,"0"),"") -> 2176 | D29: =IF(2<=$B$8,TEXT(2*($B$18-$B$7),"0.0")&" years ahead of staying home","") -> 30.9 years ahead of staying home
A30: =IF(3<=$B$8,3,"") -> 3 | B30: =IF(3<=$B$8,3*$B$7,"") -> 30 | C30: =IF(3<=$B$8,TEXT(Chrysalis!$B$22+3*$B$18,"0"),"") -> 2201 | D30: =IF(3<=$B$8,TEXT(3*($B$18-$B$7),"0.0")&" years ahead of staying home","") -> 46.3 years ahead of staying home
A31: =IF(4<=$B$8,4,"") -> 4 | B31: =IF(4<=$B$8,4*$B$7,"") -> 40 | C31: =IF(4<=$B$8,TEXT(Chrysalis!$B$22+4*$B$18,"0"),"") -> 2227 | D31: =IF(4<=$B$8,TEXT(4*($B$18-$B$7),"0.0")&" years ahead of staying home","") -> 61.8 years ahead of staying home
A32: =IF(5<=$B$8,5,"") -> 5 | B32: =IF(5<=$B$8,5*$B$7,"") -> 50 | C32: =IF(5<=$B$8,TEXT(Chrysalis!$B$22+5*$B$18,"0"),"") -> 2252 | D32: =IF(5<=$B$8,TEXT(5*($B$18-$B$7),"0.0")&" years ahead of staying home","") -> 77.2 years ahead of staying home
A33: =IF(6<=$B$8,6,"") | B33: =IF(6<=$B$8,6*$B$7,"") | C33: =IF(6<=$B$8,TEXT(Chrysalis!$B$22+6*$B$18,"0"),"") | D33: =IF(6<=$B$8,TEXT(6*($B$18-$B$7),"0.0")&" years ahead of staying home","")
A34: =IF(7<=$B$8,7,"") | B34: =IF(7<=$B$8,7*$B$7,"") | C34: =IF(7<=$B$8,TEXT(Chrysalis!$B$22+7*$B$18,"0"),"") | D34: =IF(7<=$B$8,TEXT(7*($B$18-$B$7),"0.0")&" years ahead of staying home","")
A35: =IF(8<=$B$8,8,"") | B35: =IF(8<=$B$8,8*$B$7,"") | C35: =IF(8<=$B$8,TEXT(Chrysalis!$B$22+8*$B$18,"0"),"") | D35: =IF(8<=$B$8,TEXT(8*($B$18-$B$7),"0.0")&" years ahead of staying home","")
A36: =IF(9<=$B$8,9,"") | B36: =IF(9<=$B$8,9*$B$7,"") | C36: =IF(9<=$B$8,TEXT(Chrysalis!$B$22+9*$B$18,"0"),"") | D36: =IF(9<=$B$8,TEXT(9*($B$18-$B$7),"0.0")&" years ahead of staying home","")
A37: =IF(10<=$B$8,10,"") | B37: =IF(10<=$B$8,10*$B$7,"") | C37: =IF(10<=$B$8,TEXT(Chrysalis!$B$22+10*$B$18,"0"),"") | D37: =IF(10<=$B$8,TEXT(10*($B$18-$B$7),"0.0")&" years ahead of staying home","")
A39: The arithmetic is brutal and honest: a ten-year ride returns fifteen Earth-years later for a mass ratio of thirty thousand — the Pendulum is the Tower with a return ticket, and the fare is why nobody runs a ferry to the future at 1 g. Short swings are nearly free (a two-year ride leads by a month) because the lead grows as sinh; the Vigil sheet sells the same future for the price of a nap. One redemption: with a Lantern mouth at each terminal the Pendulum stops being a ferry and becomes a subway.

Sheet Moult
A1: Moult — the ship that sheds its shells
A2: Chrysalis in reverse: instead of growing chambers (Nautilus), the ship jettisons each emptied shell as its people move inward or go under (Vigil), so the hull it must brake at Proxima is lighter than the hull it launched. Same fuel, same engine — the shed mass converts into cruise speed. No new physics; the quadratic below is the rocket equation with a lighter second burn.
A4: Inputs
A5: Quantity | B5: Value | C5: Unit | D5: Notes / source
A6: Fraction of dry mass moulted before the brake | B6: 0.5 | D6: Emptied shells, spent factories, outgrown nurseries — cast off after the burn out, before the brake
A7: Dry mass at launch | B7: =Chrysalis!$B$31 -> 2400000000000 | C7: kg | D7: Chrysalis sheet
A8: Fuel | B8: =Chrysalis!$B$80 -> 2.1281075e+12 | C8: kg | D8: The Chrysalis sheet's own fuel load
A9: Exhaust velocity | B9: =Chrysalis!$B$19*Constants!$B$7 -> 9983088.9 | C9: m/s
A10: Distance | B10: =Chrysalis!$B$32 -> 4e+16 | C10: m
A12: Two burns with a moult between
A13: Quantity | B13: Value | C13: Unit | D13: Notes / source
A14: Dry mass at the brake | B14: =$B$7*(1-$B$6) -> 1200000000000 | C14: kg
A15: X = e^(v/vₑ), root of M₁′X² + (M₀ − M₁′)X − (M₀ + F) = 0 | B15: =(-($B$7-$B$14)+SQRT(($B$7-$B$14)^2+4*$B$14*($B$7+$B$8)))/(2*$B$14) -> 1.5058472 | D15: Accelerate at full mass, brake at moulted mass, same total fuel
A16: Cruise speed | B16: =$B$9*LN($B$15) -> 4086633.8 | C16: m/s
A17: …as a fraction of c | B17: =$B$16/Constants!$B$7 -> 0.013631543 | C17: × c
A18: Journey time | B18: =$B$10/$B$16/Constants!$B$10 -> 310.16322 | C18: years
A19: Years saved vs Chrysalis as drawn | B19: =Chrysalis!$B$13-$B$18 -> 89.836775 | C19: years
A20: Relativistic lead at arrival, (β²/2)·T | B20: =$B$17^2/2*$B$18*365.25 -> 10.525447 | C20: days | D20: Faster and shorter, yet more lead: the rate wins over the duration
A21: Lead gained over Chrysalis | B21: ='Lead table'!$Q$5*-365.25+$B$20 -> 2.3637027 | C21: days
A22: Control: speed at 0% moult, vₑ·ln √(1+F/M₀) | B22: =$B$9*LN(SQRT(1+$B$8/$B$7))/Constants!$B$7 -> 0.010570008 | C22: × c | D22: Equals Chrysalis's β = 0.0106 exactly — the sheet contains its own control
A24: The moulting calendar — every shed fraction at once
A25: Moult fraction | B25: Cruise β | C25: Journey (yr) | D25: Years saved / lead
A26: 0.1 | B26: =$B$9*LN((-($B$7-$B$7*(1-$A26))+SQRT(($B$7-$B$7*(1-$A26))^2+4*$B$7*(1-$A26)*($B$7+$B$8)))/(2*$B$7*(1-$A26)))/Constants!$B$7 -> 0.011046841 | C26: =$B$10/($B26*Constants!$B$7)/Constants!$B$10 -> 382.73416 | D26: =TEXT(Chrysalis!$B$13-$C26,"0")&" yr saved; lead "&TEXT($B26^2/2*$C26*365.25,"0.0")&" days" -> 17 yr saved; lead 8.5 days
A27: 0.2 | B27: =$B$9*LN((-($B$7-$B$7*(1-$A27))+SQRT(($B$7-$B$7*(1-$A27))^2+4*$B$7*(1-$A27)*($B$7+$B$8)))/(2*$B$7*(1-$A27)))/Constants!$B$7 -> 0.011577851 | C27: =$B$10/($B27*Constants!$B$7)/Constants!$B$10 -> 365.18033 | D27: =TEXT(Chrysalis!$B$13-$C27,"0")&" yr saved; lead "&TEXT($B27^2/2*$C27*365.25,"0.0")&" days" -> 35 yr saved; lead 8.9 days
A28: 0.3 | B28: =$B$9*LN((-($B$7-$B$7*(1-$A28))+SQRT(($B$7-$B$7*(1-$A28))^2+4*$B$7*(1-$A28)*($B$7+$B$8)))/(2*$B$7*(1-$A28)))/Constants!$B$7 -> 0.012174453 | C28: =$B$10/($B28*Constants!$B$7)/Constants!$B$10 -> 347.28486 | D28: =TEXT(Chrysalis!$B$13-$C28,"0")&" yr saved; lead "&TEXT($B28^2/2*$C28*365.25,"0.0")&" days" -> 53 yr saved; lead 9.4 days
A29: 0.4 | B29: =$B$9*LN((-($B$7-$B$7*(1-$A29))+SQRT(($B$7-$B$7*(1-$A29))^2+4*$B$7*(1-$A29)*($B$7+$B$8)))/(2*$B$7*(1-$A29)))/Constants!$B$7 -> 0.012851955 | C29: =$B$10/($B29*Constants!$B$7)/Constants!$B$10 -> 328.97745 | D29: =TEXT(Chrysalis!$B$13-$C29,"0")&" yr saved; lead "&TEXT($B29^2/2*$C29*365.25,"0.0")&" days" -> 71 yr saved; lead 9.9 days
A30: 0.5 | B30: =$B$9*LN((-($B$7-$B$7*(1-$A30))+SQRT(($B$7-$B$7*(1-$A30))^2+4*$B$7*(1-$A30)*($B$7+$B$8)))/(2*$B$7*(1-$A30)))/Constants!$B$7 -> 0.013631543 | C30: =$B$10/($B30*Constants!$B$7)/Constants!$B$10 -> 310.16322 | D30: =TEXT(Chrysalis!$B$13-$C30,"0")&" yr saved; lead "&TEXT($B30^2/2*$C30*365.25,"0.0")&" days" -> 90 yr saved; lead 10.5 days
A31: 0.6 | B31: =$B$9*LN((-($B$7-$B$7*(1-$A31))+SQRT(($B$7-$B$7*(1-$A31))^2+4*$B$7*(1-$A31)*($B$7+$B$8)))/(2*$B$7*(1-$A31)))/Constants!$B$7 -> 0.014543753 | C31: =$B$10/($B31*Constants!$B$7)/Constants!$B$10 -> 290.70924 | D31: =TEXT(Chrysalis!$B$13-$C31,"0")&" yr saved; lead "&TEXT($B31^2/2*$C31*365.25,"0.0")&" days" -> 109 yr saved; lead 11.2 days
A32: 0.7 | B32: =$B$9*LN((-($B$7-$B$7*(1-$A32))+SQRT(($B$7-$B$7*(1-$A32))^2+4*$B$7*(1-$A32)*($B$7+$B$8)))/(2*$B$7*(1-$A32)))/Constants!$B$7 -> 0.015634959 | C32: =$B$10/($B32*Constants!$B$7)/Constants!$B$10 -> 270.41985 | D32: =TEXT(Chrysalis!$B$13-$C32,"0")&" yr saved; lead "&TEXT($B32^2/2*$C32*365.25,"0.0")&" days" -> 130 yr saved; lead 12.1 days
A33: 0.8 | B33: =$B$9*LN((-($B$7-$B$7*(1-$A33))+SQRT(($B$7-$B$7*(1-$A33))^2+4*$B$7*(1-$A33)*($B$7+$B$8)))/(2*$B$7*(1-$A33)))/Constants!$B$7 -> 0.016980811 | C33: =$B$10/($B33*Constants!$B$7)/Constants!$B$10 -> 248.98712 | D33: =TEXT(Chrysalis!$B$13-$C33,"0")&" yr saved; lead "&TEXT($B33^2/2*$C33*365.25,"0.0")&" days" -> 151 yr saved; lead 13.1 days
A34: 0.9 | B34: =$B$9*LN((-($B$7-$B$7*(1-$A34))+SQRT(($B$7-$B$7*(1-$A34))^2+4*$B$7*(1-$A34)*($B$7+$B$8)))/(2*$B$7*(1-$A34)))/Constants!$B$7 -> 0.018718212 | C34: =$B$10/($B34*Constants!$B$7)/Constants!$B$10 -> 225.87645 | D34: =TEXT(Chrysalis!$B$13-$C34,"0")&" yr saved; lead "&TEXT($B34^2/2*$C34*365.25,"0.0")&" days" -> 174 yr saved; lead 14.5 days
A36: What a moult sheds
A37: Quantity | B37: Value | C37: Unit | D37: Notes / source
A38: Mass moulted | B38: =$B$7*$B$6 -> 1200000000000 | C38: kg
A39: …per decade-watch of the Moult's own voyage | B39: =$B$38/($B$18/Vigil!$B$9) -> 3.8689306e+10 | C39: kg | D39: About 31 decade-watches fit the shorter crossing: each seals a shell, and lets it go
A40: Spacing of the cast-off shells along the route | B40: =$B$16*Vigil!$B$9*Constants!$B$10/Constants!$B$12 -> 0.13631543 | C40: ly | D40: One sealed shell adrift every so many light-years: the moult is legible from outside
A42: Nautilus and Moult are the same ship run in opposite directions: one keeps every era aboard and arrives long, the other posts its eras along the route and arrives early. The shells are not burned — a fusion drive wants deuterium, not drywall — they are simply never braked: cast off at cruise speed, they sweep through the Proxima system unbraked at the same ~310-year mark as the crew's arrival and keep going forever — a museum that never stops at its own opening. The ninety years is what the moult saves against Chrysalis's 400-year schedule, not a delay of the shells.

Sheet Lighthouse
A1: Lighthouse — the broadcast: the core is a clock and a laser
A2: The cheapest time ship is the one Earth watches. Put the project's clocks in the core and a laser on the stern, and the voyage becomes a live broadcast from a slower stream of time: every ship-day arrives stretched by the Doppler factor k, and the whole 400-year crossing airs over 404. Nothing new flies — Chrysalis already carries the comms; this sheet points it home and does the bookkeeping.
A4: Inputs
A5: Quantity | B5: Value | C5: Unit | D5: Notes / source
A6: Transmitter power | B6: 1 | C6: kW | D6: A laser the size of a streetlight
A7: Transmitter aperture | B7: 1 | C7: m | D7: Assumption
A8: Receiver aperture at Earth | B8: 39 | C8: m | D8: The ELT's mirror; any century that can build a Chrysalis keeps a telescope this size
A9: Wavelength | B9: 1064 | C9: nm | D9: Nd:YAG
A10: Cruise β | B10: =Chrysalis!$B$36 -> 0.010570008 | C10: × c | D10: Chrysalis sheet
A12: The slow-motion channel
A13: Quantity | B13: Value | C13: Unit | D13: Notes / source
A14: Doppler factor k = √((1+β)/(1−β)) | B14: =SQRT((1+$B$10)/(1-$B$10)) -> 1.0106265 | D14: Recession: BOTH ends see the other slowed by k; the asymmetry settles only when the clocks stand still together
A15: Slow motion Earth sees | B15: =1/$B$14 -> 0.98948527 | D15: Ship-seconds per Earth-second on the live feed
A16: The 400 ship-years air over | B16: =Chrysalis!$B$64*$B$14 -> 404.228 | C16: years
A17: Stretch — extra broadcast years | B17: =$B$16-Chrysalis!$B$64 -> 4.250349 | C17: years | D17: Exactly the final light-time plus the relativistic lead: 4.23 + 0.02 years. The bookkeeping closes.
A18: Final latency | B18: =Chrysalis!$B$33 -> 4.2280033 | C18: years | D18: Every hello from Proxima is this stale
A19: First round-trip conversation | B19: =2*$B$18 -> 8.4560067 | C19: years
A21: The link budget — photons across four light-years
A22: Quantity | B22: Value | C22: Unit | D22: Notes / source
A23: Received power, P·π²·D_t²·D_r² / (16 λ² d²) | B23: =$B$6*1000*PI()^2*$B$7^2*$B$8^2/(16*($B$9*0.000000001)^2*(Chrysalis!$B$33*Constants!$B$12)^2) -> 5.1797135e-16 | C23: W | D23: Diffraction-limited aperture to aperture, at the full Proxima distance
A24: …as photons per second | B24: =$B$23/(Constants!$B$52*Constants!$B$7/($B$9*0.000000001)) -> 2774.41 | C24: photons/s | D24: Thousands per second at four light-years from a streetlight: a telemetry channel, a slideshow, a will
A25: Bits per second at 10 photons per bit | B25: =$B$24/10 -> 277.441 | C25: bit/s | D25: Photon-starved but ample for clocks, logs and letters
A27: The programme guide
A28: Ship year | B28: Airs at Earth, calendar year | C28: Latency then (yr) | D28: What the audience is watching
A29: 0 | B29: =TEXT(Chrysalis!$B$22+$A29*$B$14,"0") -> 2125 | C29: =$A29*$B$10/SQRT(1-$B$10^2) -> 0 | D29: Departure, live from the L1 yard
A30: 100 | B30: =TEXT(Chrysalis!$B$22+$A30*$B$14,"0") -> 2226 | C30: =$A30*$B$10/SQRT(1-$B$10^2) -> 1.0570599 | D30: The great-grandchildren of the launch crew; nobody aboard remembers Earth
A31: 200 | B31: =TEXT(Chrysalis!$B$22+$A31*$B$14,"0") -> 2327 | C31: =$A31*$B$10/SQRT(1-$B$10^2) -> 2.1141198 | D31: Halfway: the turn of the ship's one long year
A32: 300 | B32: =TEXT(Chrysalis!$B$22+$A32*$B$14,"0") -> 2428 | C32: =$A32*$B$10/SQRT(1-$B$10^2) -> 3.1711797 | D32: Voices with an accent no linguist on Earth has heard spoken
A33: 400 | B33: =TEXT(Chrysalis!$B$22+$A33*$B$14,"0") -> 2529 | C33: =$A33*$B$10/SQRT(1-$B$10^2) -> 4.2282395 | D33: Arrival — the audience learns of it 4.2 years after the crew
A35: The channel runs both ways: Earth's lighthouse uplinks the archive, and the ship receives history at the same slow-motion factor — by arrival the crew are 4.23 years behind the news and 8.2 days younger than the calendar. During the cruise each end honestly sees the other slowed; relativity keeps the books symmetric until somebody turns around. Every core in this workbook should carry the Lighthouse as its black box: it is the only design whose time travel the people left behind get to share.

Sheet Sundiver
A1: Sundiver — the homebody: the core is a heat shield
A2: The time ship that never leaves. Drop the perihelion toward the Sun and every orbit banks a little lead — speed and depth pay together, and over a Kepler orbit the virial theorem collapses the whole bank to one number, the semi-major axis: ⟨v²/2 + GM/r⟩ = 3GM/2a. This sheet runs the dive and then says the honest thing: the well loses to the wheel.
A4: Inputs
A5: Quantity | B5: Value | C5: Unit | D5: Notes / source
A6: Perihelion | B6: 4 | C6: R☉ | D6: Parker Solar Probe survived 9.86 R☉ at 1,400 K; 4 is a bolder shield
A7: Aphelion | B7: 1 | C7: AU | D7: The dive starts from home
A8: Years of service | B8: =Chrysalis!$B$13 -> 400 | C8: years | D8: The span of the Chrysalis crossing, for the comparison
A10: The orbit and the bank
A11: Quantity | B11: Value | C11: Unit | D11: Notes / source
A12: Perihelion | B12: =$B$6*Constants!$B$53 -> 2782800000 | C12: m
A13: Semi-major axis a | B13: =($B$12+$B$7*Constants!$B$13)/2 -> 76190335350 | C13: m
A14: Orbit period, 2π√(a³/GM) | B14: =2*PI()*SQRT($B$13^3/Constants!$B$14)/Constants!$B$10 -> 0.36347112 | C14: years
A15: Perihelion speed, √(GM(2/r − 1/a)) | B15: =SQRT(Constants!$B$14*(2/$B$12-1/$B$13))/1000 -> 306.00434 | C15: km/s | D15: Beats Parker's 192 km/s record for any perihelion inside ~10 R☉
A16: Time-averaged slowdown vs Earth, (3GM/2c²)(1/a − 1/AU) | B16: =1.5*Constants!$B$14/Constants!$B$7^2*(1/$B$13-1/Constants!$B$13) -> 1.4265166e-08 | C16: fraction | D16: ⟨v²/2⟩ = GM/2a and ⟨GM/r⟩ = GM/a over a Kepler orbit; Earth's own orbit cancels in the difference. Checked against a numerical orbit integral to 10⁻⁵.
A17: …per day | B17: =$B$16*Constants!$B$11*1000 -> 1.2325104 | C17: ms/day
A18: Banked per orbit | B18: =$B$16*$B$14*Constants!$B$10 -> 0.1636254 | C18: s
A19: Banked over the service life | B19: =$B$16*$B$8*Constants!$B$10 -> 180.06976 | C19: s | D19: Three minutes per four centuries
A20: Blackbody equilibrium at perihelion, 279 K/√(r/AU) | B20: =Constants!$B$54/SQRT($B$12/Constants!$B$13) -> 2045.6245 | C20: K | D20: Isothermal-sphere blackbody, zero albedo; a sun-facing insulated shield runs up to 4^¼ ≈ 1.41× hotter — Parker's TPS design temperature was ~1,644 K at 9.86 R☉
A22: The verdict
A23: Quantity | B23: Value | C23: Unit | D23: Notes / source
A24: Chrysalis's coasting rate, β²/2 | B24: =Chrysalis!$B$36^2/2 -> 5.5862538e-05 | C24: fraction
A25: The wheel beats the well by | B25: =$B$24/$B$16 -> 3916.0104 | C25: × | D25: Coasting at 1% of c out-dilates a Sun-grazing orbit four-thousandfold: the solar potential is shallow, and a diver must keep returning to 1 AU to stay a ship
A26: A circular orbit matching Chrysalis would sit at | B26: =1/($B$24*2*Constants!$B$7^2/(3*Constants!$B$14)+1/Constants!$B$13)/Constants!$B$53 -> 0.056977544 | C26: R☉ | D26: Inside the Sun's photosphere — the orbit does not exist. Case closed.
A28: Kept for the same reason the Feynman core stays in the catalogue: a correct machine with an honest, damning number. The Sundiver's customers are clocks, not crews — as a calibration source it is the best proper-time waveform in the solar system — but as a ship it is a kettle that banks three minutes per four centuries. It teaches the starship rule in reverse: gravity gives dilation free only if you stay down the well, and staying down the Sun's well is called being inside the Sun.
